Workbook

Sheet Read Me
B2: Equator Resolution — Financial & Loan Unit-Economics & P&L Model
B3: A high-volume, low-ticket model tiered by matter type (OTS, cheque-bounce, grievance).
B6: HOW TO USE
B7: - Edit blue/yellow inputs on 'Assumptions'. 'Unit Economics' and 'P&L' recompute automatically.
B8: - Matter mix and monthly volume drive the P&L; find the break-even month in the P&L sheet.
B9: - All figures illustrative and must be validated against real cost and pricing data before use.

Sheet Assumptions
B2: Assumptions (edit blue/yellow)
B4: Per-matter-type revenue & cost (₹ per case)
B5: Item | C5: OTS / default | D5: Cheque (138) | E5: Grievance/DL
B6: Registration + admin fee | C6: 1800 | D6: 1200 | E6: 800
B7: Institution success/settlement fee | C7: 3000 | D7: 1500 | E7: 600
B8: Escrow handling (net to Equator) | C8: 800 | D8: 400 | E8: 0
B9: Direct neutral cost (per case) | C9: -2000 | D9: -1200 | E9: -700
B10: Direct servicing/ops cost (per case) | C10: -800 | D10: -600 | E10: -400
B12: Monthly volume & mix (steady-state)
B13: Item | C13: OTS / default | D13: Cheque (138) | E13: Grievance/DL
B14: Cases per month (steady-state) | C14: 400 | D14: 500 | E14: 250
B16: Fixed monthly costs (₹)
B17: Platform & technology | C17: 250000
B18: Core team & panel management | C18: 650000
B19: Compliance, legal & audit | C19: 180000
B20: Sales / lender BD & marketing | C20: 300000
B21: G&A / overheads | C21: 220000
B23: Total fixed monthly cost | C23: =SUM(C17:C21)
B25: Ramp: months to steady-state | C25: 12

Sheet Unit Economics
B2: Unit Economics (per case, by matter type)
B4: Item | C4: OTS / default | D4: Cheque (138) | E4: Grievance/DL
B5: Gross revenue | C5: =Assumptions!C6+Assumptions!C7+Assumptions!C8 | D5: =Assumptions!D6+Assumptions!D7+Assumptions!D8 | E5: =Assumptions!E6+Assumptions!E7+Assumptions!E8
B6: Direct cost | C6: =Assumptions!C9+Assumptions!C10 | D6: =Assumptions!D9+Assumptions!D10 | E6: =Assumptions!E9+Assumptions!E10
B7: Contribution / case | C7: =C5+C6 | D7: =D5+D6 | E7: =E5+E6
B8: Contribution margin | C8: =IFERROR(C7/C5,0) | D8: =IFERROR(D7/D5,0) | E8: =IFERROR(E7/E5,0)
B10: Monthly cases | C10: =Assumptions!C14 | D10: =Assumptions!D14 | E10: =Assumptions!E14
B11: Monthly contribution | C11: =C7*C10 | D11: =D7*D10 | E11: =E7*E10
B13: Blended monthly contribution (all types) | C13: =C11+D11+E11
B14: Blended contribution / case | C14: =IFERROR((C11+D11+E11)/(C10+D10+E10),0)
B16: Contribution = revenue net of direct (per-case) costs, before fixed costs.

Sheet P&L (12-mo ramp)
B2: Monthly P&L — linear ramp to steady-state
B4: Month | C4: M1 | D4: M2 | E4: M3 | F4: M4 | G4: M5 | H4: M6 | I4: M7 | J4: M8 | K4: M9 | L4: M10 | M4: M11 | N4: M12
B5: Ramp factor | C5: =MIN(1,1/Assumptions!$C$25) | D5: =MIN(1,2/Assumptions!$C$25) | E5: =MIN(1,3/Assumptions!$C$25) | F5: =MIN(1,4/Assumptions!$C$25) | G5: =MIN(1,5/Assumptions!$C$25) | H5: =MIN(1,6/Assumptions!$C$25) | I5: =MIN(1,7/Assumptions!$C$25) | J5: =MIN(1,8/Assumptions!$C$25) | K5: =MIN(1,9/Assumptions!$C$25) | L5: =MIN(1,10/Assumptions!$C$25) | M5: =MIN(1,11/Assumptions!$C$25) | N5: =MIN(1,12/Assumptions!$C$25)
B6: Contribution (₹) | C6: ='Unit Economics'!$C$13*C5 | D6: ='Unit Economics'!$C$13*D5 | E6: ='Unit Economics'!$C$13*E5 | F6: ='Unit Economics'!$C$13*F5 | G6: ='Unit Economics'!$C$13*G5 | H6: ='Unit Economics'!$C$13*H5 | I6: ='Unit Economics'!$C$13*I5 | J6: ='Unit Economics'!$C$13*J5 | ... N6: ='Unit Economics'!$C$13*N5
B7: Fixed cost (₹) | C7: =Assumptions!$C$23 | D7: =Assumptions!$C$23 | E7: =Assumptions!$C$23 | F7: =Assumptions!$C$23 | G7: =Assumptions!$C$23 | H7: =Assumptions!$C$23 | I7: =Assumptions!$C$23 | J7: =Assumptions!$C$23 | ... N7: =Assumptions!$C$23
B8: EBITDA (₹) | C8: =C6-C7 | D8: =D6-D7 | E8: =E6-E7 | F8: =F6-F7 | G8: =G6-G7 | H8: =H6-H7 | I8: =I6-I7 | J8: =J6-J7 | ... N8: =N6-N7
B9: Cumulative EBITDA (₹) | C9: =C8 | D9: =C9+D8 | E9: =D9+E8 | F9: =E9+F8 | G9: =F9+G8 | H9: =G9+H8 | I9: =H9+I8 | J9: =I9+J8 | K9: =J9+K8 | ... N9: =M9+N8
B10: (helper: positive-EBITDA month) | C10: =IF(C8>0,1,9999) | D10: =IF(D8>0,2,9999) | E10: =IF(E8>0,3,9999) | F10: =IF(F8>0,4,9999) | G10: =IF(G8>0,5,9999) | H10: =IF(H8>0,6,9999) | I10: =IF(I8>0,7,9999) | J10: =IF(J8>0,8,9999) | K10: =IF(K8>0,9,9999) | L10: =IF(L8>0,10,9999) | M10: =IF(M8>0,11,9999) | N10: =IF(N8>0,12,9999)
B11: Break-even month (first M with positive EBITDA): | G11: =IF(MIN(C10:N10)>12,"beyond M12",MIN(C10:N10))
B13: Steady-state monthly EBITDA (₹) | G13: ='Unit Economics'!C13-Assumptions!C23
B14: Steady-state annual EBITDA (₹) | G14: =('Unit Economics'!C13-Assumptions!C23)*12
B16: Illustrative, contribution-based model; excludes taxes, capex and financing. Validate before use.
