Workbook

Sheet ReadMe
B2: Equator Resolution — Family Vertical Financial Model
B3: Illustrative model. Blue = input (edit these); black = formula. Yellow-filled cells are the key levers.
B6: HOW TO USE
B7: - Edit the blue/yellow input cells on 'Assumptions' only; every other sheet recalculates.
B8: - 'PnL' shows the 3-year revenue-to-EBITDA bridge; 'UnitEconomics' shows per-case economics and break-even;
B9: 'Sensitivity' flexes case volume (Conservative 70% / Base / Optimistic 130%).
B11: REVENUE MODEL
B12: Equator earns: registration fee, per-session case-management fee, a share of the mediator fee,
B13: and an escrow-handling fee. The mediator's own fee is treated as pass-through (only Equator's share is revenue).
B15: IMPORTANT
B16: All figures are illustrative assumptions, not projections or guarantees. Validate every input against
B17: Equator's actual tariff, costs and pipeline before relying on the output.

Sheet Assumptions
B2: Assumptions
B3: Edit blue/yellow cells only.
B4: VOLUME & ACTIVITY
B5: Cases handled — Year 1 | C5: 300
B6: Cases handled — Year 2 | C6: 750
B7: Cases handled — Year 3 | C7: 1500
B8: Average mediation sessions per case | C8: 4
B9: Parties per case | C9: 2
B11: FEES & RATES (Equator schedule)
B12: Registration fee (per party, one-time) ₹ | C12: 1000
B13: Case-management fee (per session, per party) ₹ | C13: 1000
B14: Mediator fee (per session, per party, blended) ₹ | C14: 3000
B15: Equator share of mediator fee | C15: 0.2
B16: Avg escrow amount (per case with money leg) ₹ | C16: 500000
B17: Escrow handling fee (% of amount) | C17: 0.005
B18: Share of cases with an escrow leg | C18: 0.6
B19: Variable cost per case (gateway, comms, e-stamp) ₹ | C19: 500
B21: ANNUAL FIXED COSTS ₹ | C21: Year 1 | D21: Year 2 | E21: Year 3
B22: Technology & platform | C22: 2500000 | D22: 3500000 | E22: 5000000
B23: Salaries (operations & case managers) | C23: 3600000 | D23: 6000000 | E23: 9600000
B24: Mediator panel & training | C24: 800000 | D24: 1200000 | E24: 1800000
B25: Marketing & business development | C25: 2500000 | D25: 3500000 | E25: 5000000
B26: Legal & compliance | C26: 800000 | D26: 1000000 | E26: 1200000
B27: Admin & overhead | C27: 1200000 | D27: 1600000 | E27: 2200000
B28: Total fixed costs | C28: =SUM(C22:C27) -> 11400000 | D28: =SUM(D22:D27) -> 16800000 | E28: =SUM(E22:E27) -> 24800000

Sheet PnL
B2: Profit & Loss — 3-Year Bridge
B3: All figures ₹. Black = formula (driven by Assumptions).
C4: Year 1 | D4: Year 2 | E4: Year 3
B5: Cases handled | C5: =Assumptions!C5 -> 300 | D5: =Assumptions!C6 -> 750 | E5: =Assumptions!C7 -> 1500
B7: Registration revenue | C7: =C5*Assumptions!$C$12*Assumptions!$C$9 -> 600000 | D7: =D5*Assumptions!$C$12*Assumptions!$C$9 -> 1500000 | E7: =E5*Assumptions!$C$12*Assumptions!$C$9 -> 3000000
B8: Case-management revenue | C8: =C5*Assumptions!$C$13*Assumptions!$C$8*Assumptions!$C$9 -> 2400000 | D8: =D5*Assumptions!$C$13*Assumptions!$C$8*Assumptions!$C$9 -> 6000000 | E8: =E5*Assumptions!$C$13*Assumptions!$C$8*Assumptions!$C$9 -> 12000000
B9: Mediator-share revenue | C9: =C5*Assumptions!$C$14*Assumptions!$C$8*Assumptions!$C$9*Assumptions!$C$15 -> 1440000 | D9: =D5*Assumptions!$C$14*Assumptions!$C$8*Assumptions!$C$9*Assumptions!$C$15 -> 3600000 | E9: =E5*Assumptions!$C$14*Assumptions!$C$8*Assumptions!$C$9*Assumptions!$C$15 -> 7200000
B10: Escrow-handling revenue | C10: =C5*Assumptions!$C$16*Assumptions!$C$17*Assumptions!$C$18 -> 450000 | D10: =D5*Assumptions!$C$16*Assumptions!$C$17*Assumptions!$C$18 -> 1125000 | E10: =E5*Assumptions!$C$16*Assumptions!$C$17*Assumptions!$C$18 -> 2250000
B11: Total revenue | C11: =SUM(C7:C10) -> 4890000 | D11: =SUM(D7:D10) -> 12225000 | E11: =SUM(E7:E10) -> 24450000
B13: Variable costs | C13: =-C5*Assumptions!$C$19 -> -150000 | D13: =-D5*Assumptions!$C$19 -> -375000 | E13: =-E5*Assumptions!$C$19 -> -750000
B14: Contribution | C14: =C11+C13 -> 4740000 | D14: =D11+D13 -> 11850000 | E14: =E11+E13 -> 23700000
B15: Contribution margin | C15: =C14/C11 -> 0.96932515 | D15: =D14/D11 -> 0.96932515 | E15: =E14/E11 -> 0.96932515
B17: Fixed costs | C17: =-Assumptions!C28 -> -11400000 | D17: =-Assumptions!D28 -> -16800000 | E17: =-Assumptions!E28 -> -24800000
B18: EBITDA | C18: =C14+C17 -> -6660000 | D18: =D14+D17 -> -4950000 | E18: =E14+E17 -> -1100000
B19: EBITDA margin | C19: =C18/C11 -> -1.3619632 | D19: =D18/D11 -> -0.40490798 | E19: =E18/E11 -> -0.044989775

Sheet UnitEconomics
B2: Per-Case Economics & Break-Even
B3: Year-1 fee basis. ₹.
B4: PER-CASE REVENUE
B5: Registration (per case) | C5: =Assumptions!C12*Assumptions!C9 -> 2000
B6: Case-management (per case) | C6: =Assumptions!C13*Assumptions!C8*Assumptions!C9 -> 8000
B7: Mediator share (per case) | C7: =Assumptions!C14*Assumptions!C8*Assumptions!C9*Assumptions!C15 -> 4800
B8: Escrow (per case, probability-weighted) | C8: =Assumptions!C16*Assumptions!C17*Assumptions!C18 -> 1500
B9: Total revenue per case | C9: =SUM(C5:C8) -> 16300
B10: Variable cost per case | C10: =Assumptions!C19 -> 500
B11: Contribution per case | C11: =C9-C10 -> 15800
B12: Contribution margin | C12: =C11/C9 -> 0.96932515
B14: BREAK-EVEN
B15: Year-1 fixed costs | C15: =Assumptions!C28 -> 11400000
B16: Break-even cases (Year 1) | C16: =C15/C11 -> 721.51899
B17: Year-1 planned cases | C17: =Assumptions!C5 -> 300
B18: Margin of safety (cases) | C18: =C17-C16 -> -421.51899

Sheet Sensitivity
B2: EBITDA Sensitivity to Case Volume
B3: EBITDA (₹) if actual volume differs from plan.
B4: Scenario | C4: Factor | D4: Year 1 EBITDA | E4: Year 2 EBITDA | F4: Year 3 EBITDA
B5: Conservative | C5: 0.7 | D5: =UnitEconomics!$C$11*Assumptions!$C$5*$C5-Assumptions!$C$28 -> -8082000 | E5: =UnitEconomics!$C$11*Assumptions!$C$6*$C5-Assumptions!$D$28 -> -8505000 | F5: =UnitEconomics!$C$11*Assumptions!$C$7*$C5-Assumptions!$E$28 -> -8210000
B6: Base case | C6: 1 | D6: =UnitEconomics!$C$11*Assumptions!$C$5*$C6-Assumptions!$C$28 -> -6660000 | E6: =UnitEconomics!$C$11*Assumptions!$C$6*$C6-Assumptions!$D$28 -> -4950000 | F6: =UnitEconomics!$C$11*Assumptions!$C$7*$C6-Assumptions!$E$28 -> -1100000
B7: Optimistic | C7: 1.3 | D7: =UnitEconomics!$C$11*Assumptions!$C$5*$C7-Assumptions!$C$28 -> -5238000 | E7: =UnitEconomics!$C$11*Assumptions!$C$6*$C7-Assumptions!$D$28 -> -1395000 | F7: =UnitEconomics!$C$11*Assumptions!$C$7*$C7-Assumptions!$E$28 -> 6010000
B9: Note: revenue scales with case volume; fixed costs held constant per year.
