Workbook

Sheet Read Me
B2: Equator Resolution — Insurance Enterprise & AI Risk Register
B3: Severity × likelihood, with owners, controls and review dates.
B6: SCORING
B7: Severity 1–5 (5 = severe: regulatory action, direct harm to a party, or health-data breach).
B8: Likelihood 1–5 (5 = expected). Score = severity × likelihood.
B9: Score ≥ 15 = Board-level. 9–14 = executive. ≤ 8 = managed at function level.
B11: THE TWO RISKS THAT DEFINE THIS VERTICAL
B12: IN-R-01 A retail policyholder routed into arbitration.
B13: IN-R-02 An Ombudsman one-year window expiring during an Equator mediation.
B14: Both are scored severity 5 and both have controls in code, not merely in policy.

Sheet Risk Register
A1: Insurance Enterprise & AI Risk Register
A2: Score = severity × likelihood. Tier is computed. Law stated as at July 2026.
A3: ID | B3: Category | C3: Risk | D3: Sev | E3: Lik | F3: Score | G3: Tier | H3: Controls | I3: Owner | J3: Review | K3: Status
A4: IN-R-01 | B4: Regulatory | C4: A retail policyholder is routed into arbitration | D4: 5 | E4: 2 | F4: =D4*E4 | G4: =IF(F4>=15,"BOARD",IF(F4>=9,"EXECUTIVE","FUNCTION")) | H4: DB CHECK constraint; API 409; AI route set; mandatory classification with second-officer review; UAT U-05 and U-36 are release gates | I4: Head of Legal | J4: Each release | K4: Open
A5: IN-R-02 | B5: Party harm | C5: An Ombudsman one-year window expires during an Equator mediation | D5: 5 | E5: 2 | F5: =D5*E5 | G5: =IF(F5>=15,"BOARD",IF(F5>=9,"EXECUTIVE","FUNCTION")) | H5: Clock engine with generated expiries; 90/60/30-day alerts; blocking 60-day prompt task; closure block on unowned clocks; automatic Critical incident on unprompted expiry | I5: Head of Operations | J5: Monthly | K5: Open
A6: IN-R-03 | B6: Data | C6: Health-data breach or misuse | D6: 5 | E6: 2 | F6: =D6*E6 | G6: =IF(F6>=15,"BOARD",IF(F6>=9,"EXECUTIVE","FUNCTION")) | H6: Segregated schema and key; assignment-scoped, time-boxed access; immutable access log reviewed monthly; exclusion from analytics and AI enforced by CI scan; vertical DPIA | I6: DPO | J6: Monthly | K6: Open
A7: IN-R-04 | B7: Integrity | C7: Repeat-player capture of a neutral by an insurer | D7: 4 | E7: 4 | F7: =D7*E7 | G7: =IF(F7>=15,"BOARD",IF(F7>=9,"EXECUTIVE","FUNCTION")) | H7: 40% concentration cap as a DB constraint; rotation; cooling-off; consumer-side panel quota; quarterly publication of outcomes by insurer; no insurer-only selection | I7: Head of Panel | J7: Quarterly | K7: Open
A8: IN-R-05 | B8: Regulatory | C8: Equator is perceived as, or presents itself as, an official forum | D8: 5 | E8: 2 | F8: =D8*E8 | G8: =IF(F8>=15,"BOARD",IF(F8>=9,"EXECUTIVE","FUNCTION")) | H8: Standing signposting script delivered verbatim and recorded; brand and marketing review; AI guardrail IN-G-07 with four adversarial cases; footer disclaimer on every page | I8: Head of Legal | J8: Quarterly | K8: Open
A9: IN-R-06 | B9: Legal | C9: A settlement purports to waive a non-waivable statutory right | D9: 4 | E9: 2 | F9: =D9*E9 | G9: =IF(F9>=15,"BOARD",IF(F9>=9,"EXECUTIVE","FUNCTION")) | H9: DB CHECK constraints (no_statutory_waiver, no_future_discharge); template control; neutral training; QA sample | I9: Head of Legal | J9: Each release | K9: Open
A10: IN-R-07 | B10: Party harm | C10: A discharge voucher is signed under compulsion without reservation | D10: 4 | E10: 3 | F10: =D10*E10 | G10: =IF(F10>=15,"BOARD",IF(F10>=9,"EXECUTIVE","FUNCTION")) | H10: Form F-I17 tick-box; DB constraint requiring a reserved balance on under_protest; case-manager script; QA sample of closed cases where the amount was disputed | I10: Head of Operations | J10: Monthly | K10: Open
A11: IN-R-08 | B11: AI | C11: The AI gives a merits opinion or a claim valuation | D11: 4 | E11: 3 | F11: =D11*E11 | G11: =IF(F11>=15,"BOARD",IF(F11>=9,"EXECUTIVE","FUNCTION")) | H11: Guardrails IN-G-03 and IN-G-04 with eight adversarial cases; 403 refusal; architectural separation of classification from routing; degradation path to the deterministic questionnaire | I11: Head of Technology | J11: Each release | K11: Open
A12: IN-R-09 | B12: Legal | C12: A fraud allegation is mediated | D12: 4 | E12: 2 | F12: =D12*E12 | G12: =IF(F12>=15,"BOARD",IF(F12>=9,"EXECUTIVE","FUNCTION")) | H12: Triage screen-out; DB constraint (no mediation route where fraud_alleged); neutral standing instruction; escalation to Head of Legal | I12: Head of Legal | J12: Monthly | K12: Open
A13: IN-R-10 | B13: Commercial | C13: Insurers decline to participate at scale | D13: 3 | E13: 4 | F13: =D13*E13 | G13: =IF(F13>=15,"BOARD",IF(F13>=9,"EXECUTIVE","FUNCTION")) | H13: Lead with the batched settlement day, which has an explicit cost case; publish participation rates; protocol template with reciprocal undertakings | I13: Head of BD | J13: Monthly | K13: Open
A14: IN-R-11 | B14: Commercial | C14: The insurer relationship is bought at the cost of process integrity | D14: 5 | E14: 2 | F14: =D14*E14 | G14: =IF(F14>=15,"BOARD",IF(F14>=9,"EXECUTIVE","FUNCTION")) | H14: Standing Board instruction: no commercial arrangement may relax the three controls; refusals recorded and reported to the Board; fee cannot be linked to the settlement amount (Rule 27) | I14: CEO | J14: Quarterly | K14: Open
A15: IN-R-12 | B15: Regulatory | C15: Regulatory change (internal ombudsman guidelines, DPDP phasing, 2025 Act commencement) | D15: 3 | E15: 5 | F15: =D15*E15 | G15: =IF(F15>=15,"BOARD",IF(F15>=9,"EXECUTIVE","FUNCTION")) | H15: Six-monthly review with named owners; every affected document listed in the [verify] register; triage logic and signposting table designed to be reconfigured, not rewritten | I15: Head of Legal | J15: Six-monthly | K15: Open
... A23: IN-R-20 | B23: Third party | C23: A broker or hospital channel partner is perceived to influence outcomes | D23: 3 | E23: 3 | F23: =D23*E23 | G23: =IF(F23>=15,"BOARD",IF(F23>=9,"EXECUTIVE","FUNCTION")) | H23: No fee sharing on referrals; no referrer role in neutral selection; a broker whose own conduct is in issue participates only as a party | I23: Head of BD | J23: Quarterly | K23: Open

Sheet Heat Map
A1: Severity × Likelihood Heat Map
A2: Count of risks in each cell.
A3: Severity \ Likelihood | B3: 1 | C3: 2 | D3: 3 | E3: 4 | F3: 5
A4: 5 | B4: =COUNTIFS('Risk Register'!$D$4:$D$23,5,'Risk Register'!$E$4:$E$23,1) | C4: =COUNTIFS('Risk Register'!$D$4:$D$23,5,'Risk Register'!$E$4:$E$23,2) | D4: =COUNTIFS('Risk Register'!$D$4:$D$23,5,'Risk Register'!$E$4:$E$23,3) | E4: =COUNTIFS('Risk Register'!$D$4:$D$23,5,'Risk Register'!$E$4:$E$23,4) | F4: =COUNTIFS('Risk Register'!$D$4:$D$23,5,'Risk Register'!$E$4:$E$23,5)
A5: 4 | B5: =COUNTIFS('Risk Register'!$D$4:$D$23,4,'Risk Register'!$E$4:$E$23,1) | C5: =COUNTIFS('Risk Register'!$D$4:$D$23,4,'Risk Register'!$E$4:$E$23,2) | D5: =COUNTIFS('Risk Register'!$D$4:$D$23,4,'Risk Register'!$E$4:$E$23,3) | E5: =COUNTIFS('Risk Register'!$D$4:$D$23,4,'Risk Register'!$E$4:$E$23,4) | F5: =COUNTIFS('Risk Register'!$D$4:$D$23,4,'Risk Register'!$E$4:$E$23,5)
A6: 3 | B6: =COUNTIFS('Risk Register'!$D$4:$D$23,3,'Risk Register'!$E$4:$E$23,1) | C6: =COUNTIFS('Risk Register'!$D$4:$D$23,3,'Risk Register'!$E$4:$E$23,2) | D6: =COUNTIFS('Risk Register'!$D$4:$D$23,3,'Risk Register'!$E$4:$E$23,3) | E6: =COUNTIFS('Risk Register'!$D$4:$D$23,3,'Risk Register'!$E$4:$E$23,4) | F6: =COUNTIFS('Risk Register'!$D$4:$D$23,3,'Risk Register'!$E$4:$E$23,5)
A7: 2 | B7: =COUNTIFS('Risk Register'!$D$4:$D$23,2,'Risk Register'!$E$4:$E$23,1) | C7: =COUNTIFS('Risk Register'!$D$4:$D$23,2,'Risk Register'!$E$4:$E$23,2) | D7: =COUNTIFS('Risk Register'!$D$4:$D$23,2,'Risk Register'!$E$4:$E$23,3) | E7: =COUNTIFS('Risk Register'!$D$4:$D$23,2,'Risk Register'!$E$4:$E$23,4) | F7: =COUNTIFS('Risk Register'!$D$4:$D$23,2,'Risk Register'!$E$4:$E$23,5)
A8: 1 | B8: =COUNTIFS('Risk Register'!$D$4:$D$23,1,'Risk Register'!$E$4:$E$23,1) | C8: =COUNTIFS('Risk Register'!$D$4:$D$23,1,'Risk Register'!$E$4:$E$23,2) | D8: =COUNTIFS('Risk Register'!$D$4:$D$23,1,'Risk Register'!$E$4:$E$23,3) | E8: =COUNTIFS('Risk Register'!$D$4:$D$23,1,'Risk Register'!$E$4:$E$23,4) | F8: =COUNTIFS('Risk Register'!$D$4:$D$23,1,'Risk Register'!$E$4:$E$23,5)

Sheet Control Map
A1: Risk to Control Mapping
A2: Every risk maps to a numbered control in the compliance workbook.
A3: Risk | B3: Control ID | C3: Control | D3: Enforcement layer | E3: Test
A4: IN-R-01 | B4: IN-C-03 | C4: No arbitration route on a retail policy | D4: Database CHECK + API 409 + AI route set | E4: UAT U-05, U-36; constraint test
A5: IN-R-02 | B5: IN-C-02 | C5: Clock table complete, owned and alerted | D5: Database GENERATED + trigger + scheduler | E5: UAT U-11, U-12, U-31; clock cases C-09 to C-12
A6: IN-R-03 | B6: IN-C-05 / IN-C-06 | C6: Health data segregated and excluded | D6: Separate schema and key; CI scan | E6: UAT U-15 to U-17, U-34
A7: IN-R-04 | B7: IN-C-07 | C7: Concentration cap, rotation, publication | D7: Database CHECK + panel system | E7: UAT U-21, U-22
A8: IN-R-05 | B8: IN-C-01 | C8: Signposting delivered and recorded | D8: Application + trigger + call sampling | E8: UAT U-01, U-07; guardrail G-07
A9: IN-R-06 | B9: IN-C-04 | C9: No waiver of a non-waivable right | D9: Database CHECK | E9: UAT U-24, U-25
A10: IN-R-07 | B10: IN-C-08 | C10: Voucher basis recorded | D10: Database CHECK | E10: UAT U-27, U-28
A11: IN-R-08 | B11: IN-C-11 | C11: AI guardrails | D11: Architecture + harness in CI | E11: Guardrail suite
A12: IN-R-09 | B12: IN-C-09 | C12: Fraud screened out of mediation | D12: Database CHECK + triage rule | E12: Constraint test
A13: IN-R-13 | B13: IN-C-10 | C13: Performance verified before closure | D13: Application + escrow reconciliation | E13: UAT U-33
A14: IN-R-17 | B14: IN-C-05 | C14: Retention and erasure | D14: Scheduled job + closure confirmation | E14: UAT U-33
A15: IN-R-19 | B15: IN-C-12 | C15: Outcome publication with methodology | D15: Reporting pipeline | E15: UAT U-34
