Workbook

Sheet Read Me
B2: Equator Resolution — Workplace & HR Unit-Economics Model
B3: Two revenue engines: per-matter mediation, and recurring employer POSH subscriptions.
B6: HOW TO USE
B7: - Edit blue/yellow inputs on 'Assumptions'; the other sheets recompute.
B8: - The POSH subscription is the distinctive feature: it is recurring, compliance-driven and largely volume-independent.
B9: - Illustrative; validate pricing and cost against real data before use.

Sheet Assumptions
B2: Assumptions (edit blue/yellow)
B4: A. Mediation — per matter (₹)
B5: Item | C5: F&F / wages | D5: Separation | E5: Grievance
B6: Registration + administration | C6: 3000 | D6: 6000 | E6: 2500
B7: Neutral fee (net to Equator share) | C7: 3000 | D7: 6000 | E7: 2500
B8: Escrow handling | C8: 600 | D8: 900 | E8: 0
B9: Direct neutral cost | C9: -3600 | D9: -7200 | E9: -3000
B10: Direct servicing cost | C10: -900 | D10: -1200 | E10: -700
B12: B. Monthly matter volume (steady state)
B13: Item | C13: F&F / wages | D13: Separation | E13: Grievance
B14: Matters per month | C14: 120 | D14: 45 | E14: 60
B16: C. POSH subscriptions (employers)
B17: Employers subscribed (steady state) | C17: 300
B18: Annual retainer per employer (₹) | C18: 60000
B19: Training / awareness revenue per employer per year (₹) | C19: 35000
B20: Direct cost per employer per year (external member + delivery) (₹) | C20: -45000
B22: D. Fixed monthly costs (₹)
B23: Platform & technology | C23: 200000
B24: Core team & panel management | C24: 700000
B25: Compliance, legal & audit | C25: 150000
B26: Sales / employer BD | C26: 350000
B27: G&A | C27: 200000
B29: Total fixed monthly cost | C29: =SUM(C23:C27)
B31: Ramp: months to steady state | C31: 12

Sheet Unit Economics
B2: Unit Economics
B4: Item | C4: F&F / wages | D4: Separation | E4: Grievance
B5: Gross revenue | C5: =Assumptions!C6+Assumptions!C7+Assumptions!C8 | D5: =Assumptions!D6+Assumptions!D7+Assumptions!D8 | E5: =Assumptions!E6+Assumptions!E7+Assumptions!E8
B6: Direct cost | C6: =Assumptions!C9+Assumptions!C10 | D6: =Assumptions!D9+Assumptions!D10 | E6: =Assumptions!E9+Assumptions!E10
B7: Contribution / matter | C7: =C5+C6 | D7: =D5+D6 | E7: =E5+E6
B8: Contribution margin | C8: =IFERROR(C7/C5,0) | D8: =IFERROR(D7/D5,0) | E8: =IFERROR(E7/E5,0)
B10: Monthly matters | C10: =Assumptions!C14 | D10: =Assumptions!D14 | E10: =Assumptions!E14
B11: Monthly contribution | C11: =C7*C10 | D11: =D7*D10 | E11: =E7*E10
B13: Mediation monthly contribution | C13: =C11+D11+E11
B15: POSH — annual contribution per employer | C15: =Assumptions!C18+Assumptions!C19+Assumptions!C20
B16: POSH — monthly contribution (all employers) | C16: =(Assumptions!C18+Assumptions!C19+Assumptions!C20)*Assumptions!C17/12
B18: TOTAL monthly contribution | C18: =C13+C16
B19: Share from recurring POSH subscriptions | C19: =IFERROR(C16/C18,0)
B21: The POSH subscription line is recurring and compliance-driven — it does not depend on dispute volume.

Sheet P&L (12-mo ramp)
B2: Monthly P&L — linear ramp
B4: Month | C4: M1 | D4: M2 | E4: M3 | F4: M4 | G4: M5 | H4: M6 | I4: M7 | J4: M8 | K4: M9 | L4: M10 | M4: M11 | N4: M12
B5: Ramp factor | C5: =MIN(1,1/Assumptions!$C$31) | D5: =MIN(1,2/Assumptions!$C$31) | E5: =MIN(1,3/Assumptions!$C$31) | F5: =MIN(1,4/Assumptions!$C$31) | G5: =MIN(1,5/Assumptions!$C$31) | H5: =MIN(1,6/Assumptions!$C$31) | I5: =MIN(1,7/Assumptions!$C$31) | J5: =MIN(1,8/Assumptions!$C$31) | K5: =MIN(1,9/Assumptions!$C$31) | L5: =MIN(1,10/Assumptions!$C$31) | M5: =MIN(1,11/Assumptions!$C$31) | N5: =MIN(1,12/Assumptions!$C$31)
B6: Contribution (₹) | C6: ='Unit Economics'!$C$18*C5 | D6: ='Unit Economics'!$C$18*D5 | E6: ='Unit Economics'!$C$18*E5 | F6: ='Unit Economics'!$C$18*F5 | G6: ='Unit Economics'!$C$18*G5 | H6: ='Unit Economics'!$C$18*H5 | I6: ='Unit Economics'!$C$18*I5 | J6: ='Unit Economics'!$C$18*J5 | ... N6: ='Unit Economics'!$C$18*N5
B7: Fixed cost (₹) | C7: =Assumptions!$C$29 | D7: =Assumptions!$C$29 | E7: =Assumptions!$C$29 | F7: =Assumptions!$C$29 | G7: =Assumptions!$C$29 | H7: =Assumptions!$C$29 | I7: =Assumptions!$C$29 | J7: =Assumptions!$C$29 | ... N7: =Assumptions!$C$29
B8: EBITDA (₹) | C8: =C6-C7 | D8: =D6-D7 | E8: =E6-E7 | F8: =F6-F7 | G8: =G6-G7 | H8: =H6-H7 | I8: =I6-I7 | J8: =J6-J7 | ... N8: =N6-N7
B9: (helper: positive month) | C9: =IF(C8>0,1,9999) | D9: =IF(D8>0,2,9999) | E9: =IF(E8>0,3,9999) | F9: =IF(F8>0,4,9999) | G9: =IF(G8>0,5,9999) | H9: =IF(H8>0,6,9999) | I9: =IF(I8>0,7,9999) | J9: =IF(J8>0,8,9999) | K9: =IF(K8>0,9,9999) | L9: =IF(L8>0,10,9999) | M9: =IF(M8>0,11,9999) | N9: =IF(N8>0,12,9999)
B11: Break-even month | G11: =IF(MIN(C9:N9)>12,"beyond M12",MIN(C9:N9))
B12: Steady-state monthly EBITDA (₹) | G12: ='Unit Economics'!C18-Assumptions!C29
B13: Steady-state annual EBITDA (₹) | G13: =('Unit Economics'!C18-Assumptions!C29)*12
