Workbook

Sheet 0. Read me
A1: EQUATOR RESOLUTION — Financial Model (EQR-17)
A2: Driver-based 5-year model · v2.0 · 8 July 2026 · Confidential · Units in ₹ lakh unless noted (1 lakh = ₹100,000).
A4: Purpose | B4: Illustrative driver-based model for the Equator Resolution platform across its six lines of business.
A5: How to use | B5: Change only the BLUE inputs on ‘1. Drivers'. All other sheets are BLACK formulas that recalculate.
A6: Colour key | B6: Blue = input you can change · Black = formula · Green = cross-sheet link.
A7: Units | B7: ₹ lakh unless a row says otherwise (counts, ₹ per unit, or %).
A8: Caveat | B8: Assumptions are indicative and NOT a forecast or projection of actual results; re-verify before external use.
A9: Sheets | B9: 1 Drivers · 2 Revenue · 3 Unit Economics · 4 Costs & Headcount · 5 P&L · 6 Summary.

Sheet 1. Drivers
A1: 1 · Drivers (inputs)
A2: Change the BLUE cells. Units noted per row.
A3: Line item | B3: FY27 | C3: FY28 | D3: FY29 | E3: FY30 | F3: FY31
A5: VOLUME — cases resolved (units)
A6: NBFC / lending | B6: 5000 | C6: 25000 | D6: 80000 | E6: 180000 | F6: 320000
A7: Commercial / MSME | B7: 300 | C7: 1200 | D7: 3500 | E7: 7000 | F7: 12000
A8: Family / matrimonial | B8: 200 | C8: 900 | D8: 2500 | E8: 5000 | F8: 8500
A9: Consumer | B9: 500 | C9: 3000 | D9: 12000 | E9: 30000 | F9: 60000
A10: Securities (SEBI) | B10: 100 | C10: 600 | D10: 2000 | E10: 4500 | F10: 8000
A11: International | B11: 20 | C11: 120 | D11: 400 | E11: 900 | F11: 1600
A13: PRICE — avg realised revenue per case (₹)
A14: NBFC / lending | B14: 1200 | C14: 1200 | D14: 1150 | E14: 1100 | F14: 1050
A15: Commercial / MSME | B15: 18000 | C15: 17500 | D15: 17000 | E15: 16500 | F15: 16000
A16: Family / matrimonial | B16: 12000 | C16: 11500 | D16: 11000 | E16: 11000 | F16: 11000
A17: Consumer | B17: 900 | C17: 900 | D17: 850 | E17: 800 | F17: 800
A18: Securities (SEBI) | B18: 9000 | C18: 9000 | D18: 8800 | E18: 8600 | F18: 8500
A19: International | B19: 150000 | C19: 150000 | D19: 145000 | E19: 140000 | F19: 140000
A21: RECURRING & OTHER LOBs
A22: Private Court tenants (count) | B22: 20 | C22: 80 | D22: 220 | E22: 450 | F22: 800
A23: Private Court ARPU (₹/yr) | B23: 60000 | C23: 60000 | D23: 60000 | E23: 60000 | F23: 60000
A24: Enterprise/API contracts (count) | B24: 3 | C24: 12 | D24: 30 | E24: 60 | F24: 110
A25: Enterprise ACV (₹/yr) | B25: 800000 | C25: 900000 | D25: 1000000 | E25: 1100000 | F25: 1200000
A26: Academy enrolments (units) | B26: 300 | C26: 900 | D26: 2000 | E26: 3500 | F26: 5500
A27: Academy fee (₹) | B27: 25000 | C27: 25000 | D27: 26000 | E27: 27000 | F27: 28000
A28: Grievance/POSH seats (count) | B28: 2000 | C28: 8000 | D28: 25000 | E28: 60000 | F28: 120000
A29: Grievance ARPU (₹/seat/yr) | B29: 300 | C29: 300 | D29: 300 | E29: 300 | F29: 300
A31: ECONOMICS (%)
A32: Neutral payout (% of case revenue) | B32: 0.55 | C32: 0.55 | D32: 0.54 | E32: 0.53 | F32: 0.52
A33: Payment processing (% of revenue) | B33: 0.02 | C33: 0.02 | D33: 0.02 | E33: 0.02 | F33: 0.02
A34: Sales & marketing (% of revenue) | B34: 0.45 | C34: 0.4 | D34: 0.35 | E34: 0.3 | F34: 0.28
A36: HEADCOUNT (count) & COST
A37: Engineering & Product | B37: 8 | C37: 18 | D37: 35 | E37: 55 | F37: 80
A38: Legal & Case-ops | B38: 4 | C38: 12 | D38: 30 | E38: 60 | F38: 110
A39: Sales & Marketing | B39: 3 | C39: 8 | D39: 18 | E39: 30 | F39: 45
A40: G&A | B40: 3 | C40: 6 | D40: 12 | E40: 20 | F40: 30
A41: Avg fully-loaded cost/head (₹ lakh/yr) | B41: 18 | C41: 19 | D41: 20 | E41: 21 | F41: 22
A42: Tech & infrastructure (₹ lakh/yr) | B42: 40 | C42: 120 | D42: 300 | E42: 600 | F42: 1000
A43: Other G&A (₹ lakh/yr) | B43: 30 | C43: 60 | D43: 120 | E43: 220 | F43: 360

Sheet 2. Revenue
A1: 2 · Revenue (₹ lakh)
A2: Case revenue = cases × avg ₹ / 100,000. Recurring LOBs added below.
A3: Line item | B3: FY27 | C3: FY28 | D3: FY29 | E3: FY30 | F3: FY31
A5: Case revenue by LOB
A6: NBFC / lending | B6: ='1. Drivers'!B6*'1. Drivers'!B14/100000 | C6: ='1. Drivers'!C6*'1. Drivers'!C14/100000 | D6: ='1. Drivers'!D6*'1. Drivers'!D14/100000 | E6: ='1. Drivers'!E6*'1. Drivers'!E14/100000 | F6: ='1. Drivers'!F6*'1. Drivers'!F14/100000
A7: Commercial / MSME | B7: ='1. Drivers'!B7*'1. Drivers'!B15/100000 | C7: ='1. Drivers'!C7*'1. Drivers'!C15/100000 | D7: ='1. Drivers'!D7*'1. Drivers'!D15/100000 | E7: ='1. Drivers'!E7*'1. Drivers'!E15/100000 | F7: ='1. Drivers'!F7*'1. Drivers'!F15/100000
A8: Family / matrimonial | B8: ='1. Drivers'!B8*'1. Drivers'!B16/100000 | C8: ='1. Drivers'!C8*'1. Drivers'!C16/100000 | D8: ='1. Drivers'!D8*'1. Drivers'!D16/100000 | E8: ='1. Drivers'!E8*'1. Drivers'!E16/100000 | F8: ='1. Drivers'!F8*'1. Drivers'!F16/100000
A9: Consumer | B9: ='1. Drivers'!B9*'1. Drivers'!B17/100000 | C9: ='1. Drivers'!C9*'1. Drivers'!C17/100000 | D9: ='1. Drivers'!D9*'1. Drivers'!D17/100000 | E9: ='1. Drivers'!E9*'1. Drivers'!E17/100000 | F9: ='1. Drivers'!F9*'1. Drivers'!F17/100000
A10: Securities (SEBI) | B10: ='1. Drivers'!B10*'1. Drivers'!B18/100000 | C10: ='1. Drivers'!C10*'1. Drivers'!C18/100000 | D10: ='1. Drivers'!D10*'1. Drivers'!D18/100000 | E10: ='1. Drivers'!E10*'1. Drivers'!E18/100000 | F10: ='1. Drivers'!F10*'1. Drivers'!F18/100000
A11: International | B11: ='1. Drivers'!B11*'1. Drivers'!B19/100000 | C11: ='1. Drivers'!C11*'1. Drivers'!C19/100000 | D11: ='1. Drivers'!D11*'1. Drivers'!D19/100000 | E11: ='1. Drivers'!E11*'1. Drivers'!E19/100000 | F11: ='1. Drivers'!F11*'1. Drivers'!F19/100000
A12: Total case revenue | B12: =SUM(B6:B11) | C12: =SUM(C6:C11) | D12: =SUM(D6:D11) | E12: =SUM(E6:E11) | F12: =SUM(F6:F11)
A14: Recurring & other revenue
A15: Private Court (SaaS) | B15: ='1. Drivers'!B22*'1. Drivers'!B23/100000 | C15: ='1. Drivers'!C22*'1. Drivers'!C23/100000 | D15: ='1. Drivers'!D22*'1. Drivers'!D23/100000 | E15: ='1. Drivers'!E22*'1. Drivers'!E23/100000 | F15: ='1. Drivers'!F22*'1. Drivers'!F23/100000
A16: Enterprise / API | B16: ='1. Drivers'!B24*'1. Drivers'!B25/100000 | C16: ='1. Drivers'!C24*'1. Drivers'!C25/100000 | D16: ='1. Drivers'!D24*'1. Drivers'!D25/100000 | E16: ='1. Drivers'!E24*'1. Drivers'!E25/100000 | F16: ='1. Drivers'!F24*'1. Drivers'!F25/100000
A17: Academy | B17: ='1. Drivers'!B26*'1. Drivers'!B27/100000 | C17: ='1. Drivers'!C26*'1. Drivers'!C27/100000 | D17: ='1. Drivers'!D26*'1. Drivers'!D27/100000 | E17: ='1. Drivers'!E26*'1. Drivers'!E27/100000 | F17: ='1. Drivers'!F26*'1. Drivers'!F27/100000
A18: Grievance / POSH (SaaS) | B18: ='1. Drivers'!B28*'1. Drivers'!B29/100000 | C18: ='1. Drivers'!C28*'1. Drivers'!C29/100000 | D18: ='1. Drivers'!D28*'1. Drivers'!D29/100000 | E18: ='1. Drivers'!E28*'1. Drivers'!E29/100000 | F18: ='1. Drivers'!F28*'1. Drivers'!F29/100000
A19: Total recurring & other | B19: =SUM(B15:B18) | C19: =SUM(C15:C18) | D19: =SUM(D15:D18) | E19: =SUM(E15:E18) | F19: =SUM(F15:F18)
A21: TOTAL REVENUE | B21: =B12+B19 | C21: =C12+C19 | D21: =D12+D19 | E21: =E12+E19 | F21: =F12+F19
A22: Revenue growth % | C22: =C21/B21-1 | D22: =D21/C21-1 | E22: =E21/D21-1 | F22: =F21/E21-1

Sheet 3. Unit Economics
A1: 3 · Unit Economics
A2: Blended per-case and SaaS metrics (₹ unless %).
A3: Line item | B3: FY27 | C3: FY28 | D3: FY29 | E3: FY30 | F3: FY31
A5: Total cases (units) | B5: ='1. Drivers'!B6+'1. Drivers'!B7+'1. Drivers'!B8+'1. Drivers'!B9+'1. Drivers'!B10+'1. Drivers'!B11 | C5: ='1. Drivers'!C6+'1. Drivers'!C7+'1. Drivers'!C8+'1. Drivers'!C9+'1. Drivers'!C10+'1. Drivers'!C11 | D5: ='1. Drivers'!D6+'1. Drivers'!D7+'1. Drivers'!D8+'1. Drivers'!D9+'1. Drivers'!D10+'1. Drivers'!D11 | E5: ='1. Drivers'!E6+'1. Drivers'!E7+'1. Drivers'!E8+'1. Drivers'!E9+'1. Drivers'!E10+'1. Drivers'!E11 | F5: ='1. Drivers'!F6+'1. Drivers'!F7+'1. Drivers'!F8+'1. Drivers'!F9+'1. Drivers'!F10+'1. Drivers'!F11
A6: Case revenue (₹ lakh) | B6: ='2. Revenue'!B12 | C6: ='2. Revenue'!C12 | D6: ='2. Revenue'!D12 | E6: ='2. Revenue'!E12 | F6: ='2. Revenue'!F12
A7: Blended revenue / case (₹) | B7: =IFERROR(B6*100000/B5,0) | C7: =IFERROR(C6*100000/C5,0) | D7: =IFERROR(D6*100000/D5,0) | E7: =IFERROR(E6*100000/E5,0) | F7: =IFERROR(F6*100000/F5,0)
A8: Neutral payout / case (₹) | B8: =IFERROR(B7*'1. Drivers'!B32,0) | C8: =IFERROR(C7*'1. Drivers'!C32,0) | D8: =IFERROR(D7*'1. Drivers'!D32,0) | E8: =IFERROR(E7*'1. Drivers'!E32,0) | F8: =IFERROR(F7*'1. Drivers'!F32,0)
A9: Gross margin / case (₹) | B9: =B7-B8-B7*'1. Drivers'!B33 | C9: =C7-C8-C7*'1. Drivers'!C33 | D9: =D7-D8-D7*'1. Drivers'!D33 | E9: =E7-E8-E7*'1. Drivers'!E33 | F9: =F7-F8-F7*'1. Drivers'!F33
A10: Gross margin / case (%) | B10: =IFERROR(B9/B7,0) | C10: =IFERROR(C9/C7,0) | D10: =IFERROR(D9/D7,0) | E10: =IFERROR(E9/E7,0) | F10: =IFERROR(F9/F7,0)
A12: SaaS logos (PC+Enterprise) | B12: ='1. Drivers'!B22+'1. Drivers'!B24 | C12: ='1. Drivers'!C22+'1. Drivers'!C24 | D12: ='1. Drivers'!D22+'1. Drivers'!D24 | E12: ='1. Drivers'!E22+'1. Drivers'!E24 | F12: ='1. Drivers'!F22+'1. Drivers'!F24
A13: S&M spend, 40% to SaaS (₹ lakh) | B13: ='2. Revenue'!B21*'1. Drivers'!B34 | C13: ='2. Revenue'!C21*'1. Drivers'!C34 | D13: ='2. Revenue'!D21*'1. Drivers'!D34 | E13: ='2. Revenue'!E21*'1. Drivers'!E34 | F13: ='2. Revenue'!F21*'1. Drivers'!F34
A14: New SaaS logos (approx) | B14: =B12 | C14: =MAX(C12-B12,1) | D14: =MAX(D12-C12,1) | E14: =MAX(E12-D12,1) | F14: =MAX(F12-E12,1)
A15: Blended CAC / new logo (₹ lakh) | B15: =IFERROR(B13*0.4/B14,0) | C15: =IFERROR(C13*0.4/C14,0) | D15: =IFERROR(D13*0.4/D14,0) | E15: =IFERROR(E13*0.4/E14,0) | F15: =IFERROR(F13*0.4/F14,0)
A16: Avg SaaS ARPU (₹ lakh/yr) | B16: =IFERROR(('2. Revenue'!B15+'2. Revenue'!B16)/B12,0) | C16: =IFERROR(('2. Revenue'!C15+'2. Revenue'!C16)/C12,0) | D16: =IFERROR(('2. Revenue'!D15+'2. Revenue'!D16)/D12,0) | E16: =IFERROR(('2. Revenue'!E15+'2. Revenue'!E16)/E12,0) | F16: =IFERROR(('2. Revenue'!F15+'2. Revenue'!F16)/F12,0)
A17: LTV (ARPU × 80% GM × 4 yrs, ₹ lakh) | B17: =B16*0.8*4 | C17: =C16*0.8*4 | D17: =D16*0.8*4 | E17: =E16*0.8*4 | F17: =F16*0.8*4
A18: LTV / CAC (x) | B18: =IFERROR(B17/B15,0) | C18: =IFERROR(C17/C15,0) | D18: =IFERROR(D17/D15,0) | E18: =IFERROR(E17/E15,0) | F18: =IFERROR(F17/F15,0)

Sheet 4. Costs & Headcount
A1: 4 · Costs & Headcount (₹ lakh)
A3: Line item | B3: FY27 | C3: FY28 | D3: FY29 | E3: FY30 | F3: FY31
A5: Headcount
A6: Engineering & Product | B6: ='1. Drivers'!B37 | C6: ='1. Drivers'!C37 | D6: ='1. Drivers'!D37 | E6: ='1. Drivers'!E37 | F6: ='1. Drivers'!F37
A7: Legal & Case-ops | B7: ='1. Drivers'!B38 | C7: ='1. Drivers'!C38 | D7: ='1. Drivers'!D38 | E7: ='1. Drivers'!E38 | F7: ='1. Drivers'!F38
A8: Sales & Marketing | B8: ='1. Drivers'!B39 | C8: ='1. Drivers'!C39 | D8: ='1. Drivers'!D39 | E8: ='1. Drivers'!E39 | F8: ='1. Drivers'!F39
A9: G&A | B9: ='1. Drivers'!B40 | C9: ='1. Drivers'!C40 | D9: ='1. Drivers'!D40 | E9: ='1. Drivers'!E40 | F9: ='1. Drivers'!F40
A10: Total headcount | B10: =SUM(B6:B9) | C10: =SUM(C6:C9) | D10: =SUM(D6:D9) | E10: =SUM(E6:E9) | F10: =SUM(F6:F9)
A12: Cost lines
A13: Personnel | B13: =B10*'1. Drivers'!B41 | C13: =C10*'1. Drivers'!C41 | D13: =D10*'1. Drivers'!D41 | E13: =E10*'1. Drivers'!E41 | F13: =F10*'1. Drivers'!F41
A14: Tech & infrastructure | B14: ='1. Drivers'!B42 | C14: ='1. Drivers'!C42 | D14: ='1. Drivers'!D42 | E14: ='1. Drivers'!E42 | F14: ='1. Drivers'!F42
A15: Sales & marketing | B15: ='2. Revenue'!B21*'1. Drivers'!B34 | C15: ='2. Revenue'!C21*'1. Drivers'!C34 | D15: ='2. Revenue'!D21*'1. Drivers'!D34 | E15: ='2. Revenue'!E21*'1. Drivers'!E34 | F15: ='2. Revenue'!F21*'1. Drivers'!F34
A16: Other G&A | B16: ='1. Drivers'!B43 | C16: ='1. Drivers'!C43 | D16: ='1. Drivers'!D43 | E16: ='1. Drivers'!E43 | F16: ='1. Drivers'!F43
A17: Neutral payout (COGS) | B17: ='2. Revenue'!B12*'1. Drivers'!B32 | C17: ='2. Revenue'!C12*'1. Drivers'!C32 | D17: ='2. Revenue'!D12*'1. Drivers'!D32 | E17: ='2. Revenue'!E12*'1. Drivers'!E32 | F17: ='2. Revenue'!F12*'1. Drivers'!F32
A18: Payment processing (COGS) | B18: ='2. Revenue'!B21*'1. Drivers'!B33 | C18: ='2. Revenue'!C21*'1. Drivers'!C33 | D18: ='2. Revenue'!D21*'1. Drivers'!D33 | E18: ='2. Revenue'!E21*'1. Drivers'!E33 | F18: ='2. Revenue'!F21*'1. Drivers'!F33
A19: Total costs | B19: =SUM(B13:B18) | C19: =SUM(C13:C18) | D19: =SUM(D13:D18) | E19: =SUM(E13:E18) | F19: =SUM(F13:F18)

Sheet 5. P&L
A1: 5 · Profit & Loss (₹ lakh)
A3: Line item | B3: FY27 | C3: FY28 | D3: FY29 | E3: FY30 | F3: FY31
A5: Revenue | B5: ='2. Revenue'!B21 | C5: ='2. Revenue'!C21 | D5: ='2. Revenue'!D21 | E5: ='2. Revenue'!E21 | F5: ='2. Revenue'!F21
A6: COGS (neutral payout + processing) | B6: =-('4. Costs & Headcount'!B17+'4. Costs & Headcount'!B18) | C6: =-('4. Costs & Headcount'!C17+'4. Costs & Headcount'!C18) | D6: =-('4. Costs & Headcount'!D17+'4. Costs & Headcount'!D18) | E6: =-('4. Costs & Headcount'!E17+'4. Costs & Headcount'!E18) | F6: =-('4. Costs & Headcount'!F17+'4. Costs & Headcount'!F18)
A7: Gross profit | B7: =B5+B6 | C7: =C5+C6 | D7: =D5+D6 | E7: =E5+E6 | F7: =F5+F6
A8: Gross margin % | B8: =IFERROR(B7/B5,0) | C8: =IFERROR(C7/C5,0) | D8: =IFERROR(D7/D5,0) | E8: =IFERROR(E7/E5,0) | F8: =IFERROR(F7/F5,0)
A10: Operating expenses
A11: Personnel | B11: =-'4. Costs & Headcount'!B13 | C11: =-'4. Costs & Headcount'!C13 | D11: =-'4. Costs & Headcount'!D13 | E11: =-'4. Costs & Headcount'!E13 | F11: =-'4. Costs & Headcount'!F13
A12: Sales & marketing | B12: =-'4. Costs & Headcount'!B15 | C12: =-'4. Costs & Headcount'!C15 | D12: =-'4. Costs & Headcount'!D15 | E12: =-'4. Costs & Headcount'!E15 | F12: =-'4. Costs & Headcount'!F15
A13: Tech & infrastructure | B13: =-'4. Costs & Headcount'!B14 | C13: =-'4. Costs & Headcount'!C14 | D13: =-'4. Costs & Headcount'!D14 | E13: =-'4. Costs & Headcount'!E14 | F13: =-'4. Costs & Headcount'!F14
A14: Other G&A | B14: =-'4. Costs & Headcount'!B16 | C14: =-'4. Costs & Headcount'!C16 | D14: =-'4. Costs & Headcount'!D16 | E14: =-'4. Costs & Headcount'!E16 | F14: =-'4. Costs & Headcount'!F16
A15: Total opex | B15: =SUM(B11:B14) | C15: =SUM(C11:C14) | D15: =SUM(D11:D14) | E15: =SUM(E11:E14) | F15: =SUM(F11:F14)
A17: EBITDA | B17: =B7+B15 | C17: =C7+C15 | D17: =D7+D15 | E17: =E7+E15 | F17: =F7+F15
A18: EBITDA margin % | B18: =IFERROR(B17/B5,0) | C18: =IFERROR(C17/C5,0) | D18: =IFERROR(D17/D5,0) | E18: =IFERROR(E17/E5,0) | F18: =IFERROR(F17/F5,0)
A19: Cumulative EBITDA | B19: =B17 | C19: =B19+C17 | D19: =C19+D17 | E19: =D19+E17 | F19: =E19+F17

Sheet 6. Summary
A1: 6 · Summary
A2: Key metrics (₹ lakh unless noted).
A3: Line item | B3: FY27 | C3: FY28 | D3: FY29 | E3: FY30 | F3: FY31
A5: Total revenue | B5: ='2. Revenue'!B21 | C5: ='2. Revenue'!C21 | D5: ='2. Revenue'!D21 | E5: ='2. Revenue'!E21 | F5: ='2. Revenue'!F21
A6: Revenue growth % | B6: ='2. Revenue'!B22 | C6: ='2. Revenue'!C22 | D6: ='2. Revenue'!D22 | E6: ='2. Revenue'!E22 | F6: ='2. Revenue'!F22
A7: Gross profit | B7: ='5. P&L'!B7 | C7: ='5. P&L'!C7 | D7: ='5. P&L'!D7 | E7: ='5. P&L'!E7 | F7: ='5. P&L'!F7
A8: Gross margin % | B8: ='5. P&L'!B8 | C8: ='5. P&L'!C8 | D8: ='5. P&L'!D8 | E8: ='5. P&L'!E8 | F8: ='5. P&L'!F8
A9: EBITDA | B9: ='5. P&L'!B17 | C9: ='5. P&L'!C17 | D9: ='5. P&L'!D17 | E9: ='5. P&L'!E17 | F9: ='5. P&L'!F17
A10: EBITDA margin % | B10: ='5. P&L'!B18 | C10: ='5. P&L'!C18 | D10: ='5. P&L'!D18 | E10: ='5. P&L'!E18 | F10: ='5. P&L'!F18
A11: Cumulative EBITDA | B11: ='5. P&L'!B19 | C11: ='5. P&L'!C19 | D11: ='5. P&L'!D19 | E11: ='5. P&L'!E19 | F11: ='5. P&L'!F19
A12: Total cases (units) | B12: ='3. Unit Economics'!B5 | C12: ='3. Unit Economics'!C5 | D12: ='3. Unit Economics'!D5 | E12: ='3. Unit Economics'!E5 | F12: ='3. Unit Economics'!F5
A13: Total headcount | B13: ='4. Costs & Headcount'!B10 | C13: ='4. Costs & Headcount'!C10 | D13: ='4. Costs & Headcount'!D10 | E13: ='4. Costs & Headcount'!E10 | F13: ='4. Costs & Headcount'!F10
A14: LTV / CAC (x) | B14: ='3. Unit Economics'!B18 | C14: ='3. Unit Economics'!C18 | D14: ='3. Unit Economics'!D18 | E14: ='3. Unit Economics'!E18 | F14: ='3. Unit Economics'!F18
A16: Revenue in ₹ crore | B16: =B5/100 | C16: =C5/100 | D16: =D5/100 | E16: =E5/100 | F16: =F5/100
