Workbook

Sheet Read Me
B2: Equator Resolution — Portfolio Financial Model
B3: One consolidated view across all five verticals: shared costs allocated once, a roll-up P&L, break-even and a single funding ask.
B6: HOW IT WORKS
B7: - 'Vertical Inputs' holds each vertical's steady-state annual revenue and direct cost (from its own model).
B8: - 'Shared Costs' are the platform costs built once and allocated across verticals (the point of the shared core).
B9: - 'Roll-Up' is a 3-year consolidated P&L with a ramp; 'Consolidated' shows break-even and the funding ask.
B10: - Change the yellow cells only. Everything else is a live formula.
B12: THE POINT THIS MODEL MAKES
B13: Built as five separate businesses, the platform never covers its shared overhead.
B14: Built as one platform with shared services, the overhead is carried once and the portfolio reaches profitability.
B15: The shared core (schema_core.sql) is what makes the shared-cost line real, not aspirational.
B17: All figures INR, exclusive of GST. Illustrative — not a forecast. Requires Board approval (see [verify] register V-23).

Sheet Vertical Inputs
A1: Vertical Inputs (steady-state, annual)
A2: Each vertical's own model feeds these. Change the yellow cells.
B4: Vertical | C4: Steady-state annual revenue (Rs.) | D4: Direct cost to serve (Rs.) | E4: Contribution (Rs.) | F4: Recurring revenue share | G4: Ramp to full (mth) | H4: Note
B5: Family | C5: 42000000 | D5: 21000000 | E5: =C5-D5 | F5: 0.35 | G5: 30 | H5: Court-referral + legal-aid volume; low fee, high social value
B6: Commercial | C6: 95000000 | D6: 44000000 | E6: =C6-D6 | F6: 0.3 | G6: 24 | H6: Ad valorem; arbitration + MSME s.12A pipeline
B7: Financial | C7: 68000000 | D7: 33000000 | E7: =C7-D7 | F7: 0.55 | G7: 24 | H7: Lender subscriptions + OTS/NI-138 volume
B8: Workplace | C8: 55000000 | D8: 26000000 | E8: =C8-D8 | F8: 0.7 | G8: 24 | H8: Employer POSH subscriptions — highly recurring
B9: Insurance | C9: 119000000 | D9: 71000000 | E9: =C9-D9 | F9: 0.41 | G9: 36 | H9: Insurer subscriptions + batched settlement days
B10: PORTFOLIO | C10: =SUM(C5:C9) | D10: =SUM(D5:D9) | E10: =SUM(E5:E9) | F10: =SUMPRODUCT(C5:C9,F5:F9)/C10

Sheet Shared Costs
A1: Shared Platform Costs (annual, built once)
A2: The costs the five verticals share because they run on one core. Allocated across verticals in 'Roll-Up'.
B4: Shared cost line | C4: Annual (Rs.) | D4: Allocation | E4: Note
B5: Leadership, legal & governance (GC, CEO, Board) | C5: 14000000 | D5: by revenue | E5: Built once for all verticals
B6: Shared technology & platform (core engine, hosting, security) | C6: 12000000 | D6: by revenue | E6: schema_core + shared services
B7: Data protection, DPO & audit | C7: 4500000 | D7: by revenue | E7: One DPIA, one audit programme
B8: Panel management & the certification academy | C8: 5000000 | D8: equally | E8: ECMN/ECCN/ECFC/ECWN/ECIN
B9: Central operations & case-management platform | C9: 7000000 | D9: by revenue | E9: One console, five verticals
B10: Brand, marketing & channel (shared) | C10: 6000000 | D10: by revenue | E10: Umbrella brand + unified explorer
B11: Finance, HR & admin | C11: 5500000 | D11: by revenue
B12: TOTAL SHARED | C12: =SUM(C5:C11)

Sheet Roll-Up
A1: Consolidated Roll-Up P&L (3-year)
A2: Ramp applied to revenue & direct cost; shared cost carried in full from year 1. Live formulas.
B4: Line | C4: Year 1 | D4: Year 2 | E4: Year 3 | F4: Basis
B5: Gross revenue (all verticals, ramped) | C5: ='Vertical Inputs'!C10*0.45 | D5: ='Vertical Inputs'!C10*0.8 | E5: ='Vertical Inputs'!C10*1.0 | F5: Portfolio revenue x ramp
B6: Direct cost to serve (ramped) | C6: ='Vertical Inputs'!D10*0.45 | D6: ='Vertical Inputs'!D10*0.8 | E6: ='Vertical Inputs'!D10*1.0 | F6: Portfolio direct cost x ramp
B7: Portfolio contribution | C7: =C5-C6 | D7: =D5-D6 | E7: =E5-E6
B8: Shared platform cost (built once, full from Y1) | C8: ='Shared Costs'!C12*0.75 | D8: ='Shared Costs'!C12*0.8 | E8: ='Shared Costs'!C12*1.0 | F8: One core for five verticals
B9: EBITDA | C9: =C7-C8 | D9: =D7-D8 | E9: =E7-E8
B10: EBITDA margin | C10: =C9/C5 | D10: =D9/D5 | E10: =E9/E5
B12: Counterfactual — five separate businesses (shared cost x5)
B13: If each vertical carried its own overhead (no shared core):
B14: Duplicated overhead penalty, Year 3 | C14: ='Shared Costs'!C12*4 | D14: =4x the shared cost that the platform avoids by building once

Sheet Consolidated
A1: Consolidated — break-even & funding ask
A2: The single number the Board and investors need.
B4: Portfolio steady-state annual revenue | C4: ='Vertical Inputs'!C10 | D4: All five at full ramp
B5: Portfolio steady-state contribution | C5: ='Vertical Inputs'!E10
B6: Shared platform cost (annual) | C6: ='Shared Costs'!C12 | D6: Built once
B7: Steady-state portfolio EBITDA | C7: ='Vertical Inputs'!E10-'Shared Costs'!C12 | D7: Contribution less shared cost
B8: Steady-state EBITDA margin | C8: =('Vertical Inputs'!E10-'Shared Costs'!C12)/'Vertical Inputs'!C10
B9: Recurring revenue share (blended) | C9: ='Vertical Inputs'!F10 | D9: Subscriptions + protocols
B10: Year-3 EBITDA (from Roll-Up) | C10: =Roll-Up!E9 | D10: At 100% ramp
B11: Approx. cumulative investment to break-even | C11: 145000000 | D11: [verify — build cost + working capital + ramp losses]
B12: Indicative funding ask | C12: 200000000 | D12: [verify] Includes contingency & 18-month runway
B14: The one-line case
B15: Five verticals, one core. Each vertical is a credible business on its own; together, sharing the platform overhead once rather than five times, the portfolio reaches a healthy steady-state EBITDA margin. The shared core is not an engineering nicety — it is what turns five cost centres into one profitable institution.
