Workbook

Sheet 0. Scenario & Read me
A1: EQUATOR — Scenario Financial Model (v2)
A2: Base / Bull / Bear with sensitivity, CAC/LTV, runway & funding. BLUE = input. Change the scenario cell and all tabs update.
A4: Scenario selector
A5: Active scenario (1=Base, 2=Bull, 3=Bear) | C5: 1 | D5: ← change this
A7: Scenario multipliers (applied to Base drivers)
A8: Driver group | B8: Base | C8: Bull | D8: Bear
A9: Volume (all case counts) | B9: 1 | C9: 1.4 | D9: 0.6
A10: Price / fee realisation | B10: 1 | C10: 1.1 | D10: 0.9
A11: Cost efficiency (opex %) | B11: 1 | C11: 0.9 | D11: 1.15
A12: CAC | B12: 1 | C12: 0.85 | D12: 1.25
A14: Active multipliers (computed from selector)
A15: Volume mult | C15: =CHOOSE($C$5,B9,C9,D9) -> 1
A16: Price mult | C16: =CHOOSE($C$5,B10,C10,D10) -> 1
A17: Opex mult | C17: =CHOOSE($C$5,B11,C11,D11) -> 1
A18: CAC mult | C18: =CHOOSE($C$5,B12,C12,D12) -> 1
A20: • This v2 adds scenario analysis on top of the Base model. Pick a scenario in C5; multipliers flow into Revenue, Costs, P&L and Summary.
A21: • BLUE cells are inputs. Black are formulas. ₹1 Cr = ₹10,000,000. Figures are planning assumptions, not a forecast.
A22: • Tabs: 1 Drivers (base) · 2 Revenue · 3 Costs · 4 P&L · 5 Unit econ (CAC/LTV) · 6 Cash & runway · 7 Sensitivity · 8 Assumptions log.

Sheet 1. Drivers (base)
A1: Base Drivers
A2: Base-case assumptions (BLUE). Scenario multipliers are applied downstream, not here.
C4: Year 1 | D4: Year 2 | E4: Year 3 | F4: Year 4 | G4: Year 5
A5: Volumes (new matters / clients per year)
A6: NBFC cases | C6: 6000 | D6: 30000 | E6: 90000 | F6: 180000 | G6: 300000
A7: Commercial cases | C7: 150 | D7: 500 | E7: 1200 | F7: 2400 | G7: 4000
A8: Family cases | C8: 200 | D8: 800 | E8: 2000 | F8: 4000 | G8: 7000
A9: Enterprise grievance clients | C9: 10 | D9: 40 | E9: 120 | F9: 260 | G9: 450
A10: POSH/grievance escalations | C10: 20 | D10: 120 | E10: 400 | F10: 900 | G10: 1600
A11: Private Court subscribers | C11: 15 | D11: 80 | E11: 220 | F11: 450 | G11: 800
A12: Private Court cases | C12: 300 | D12: 2000 | E12: 6000 | F12: 14000 | G12: 26000
A13: Academy learners | C13: 300 | D13: 1200 | E13: 3000 | F13: 6000 | G13: 10000
A14: API/white-label clients | C14: 2 | D14: 8 | E14: 20 | F14: 40 | G14: 70
A15: Prices (₹ per unit)
A16: NBFC blended fee/case | C16: 2400 | D16: 2450 | E16: 2600 | F16: 2600 | G16: 2750
A17: Commercial fee/case | C17: 60000 | D17: 62000 | E17: 64000 | F17: 66000 | G17: 68000
A18: Family fee/case | C18: 18000 | D18: 18500 | E18: 19000 | F18: 19500 | G18: 20000
A19: Grievance SaaS/client | C19: 180000 | D19: 190000 | E19: 200000 | F19: 210000 | G19: 220000
A20: Escalation fee | C20: 25000 | D20: 26000 | E20: 27000 | F20: 28000 | G20: 29000
A21: Private Court subscription | C21: 60000 | D21: 63000 | E21: 66000 | F21: 69000 | G21: 72000
A22: Private Court fee/case | C22: 800 | D22: 850 | E22: 900 | F22: 950 | G22: 1000
A23: Academy fee/learner | C23: 12000 | D23: 12500 | E23: 13000 | F23: 13500 | G23: 14000
A24: API fee/client | C24: 600000 | D24: 650000 | E24: 700000 | F24: 750000 | G24: 800000
A25: Costs
A26: Headcount | C26: 18 | D26: 40 | E26: 75 | F26: 120 | G26: 170
A27: Loaded salary/head | C27: 1400000 | D27: 1450000 | E27: 1500000 | F27: 1550000 | G27: 1600000
A28: Infra/3rd-party per case | C28: 120 | D28: 110 | E28: 100 | F28: 95 | G28: 90
A29: S&M % of revenue (base) | C29: 0.45 | D29: 0.35 | E29: 0.28 | F29: 0.24 | G29: 0.22
A30: G&A % of revenue (base) | C30: 0.3 | D30: 0.22 | E30: 0.18 | F30: 0.16 | G30: 0.15
A31: Neutral payout % of case fees | C31: 0.45 | D31: 0.45 | E31: 0.44 | F31: 0.44 | G31: 0.43
A32: Unit-economics drivers
A33: Blended CAC (₹) base | C33: 1200 | D33: 1100 | E33: 1000 | F33: 950 | G33: 900
A34: Avg customer life (yrs) | C34: 2 | D34: 2.2 | E34: 2.5 | F34: 2.7 | G34: 3
A35: Contribution margin proxy | C35: 0.55 | D35: 0.56 | E35: 0.58 | F35: 0.6 | G35: 0.62

Sheet 2. Revenue
A1: Revenue (scenario-adjusted)
A2: Formula: Base volume × Volume-mult × Base price × Price-mult.
C4: Year 1 | D4: Year 2 | E4: Year 3 | F4: Year 4 | G4: Year 5
A5: NBFC fees | C5: ='1. Drivers (base)'!C6*'0. Scenario & Read me'!$C$15*'1. Drivers (base)'!C16*'0. Scenario & Read me'!$C$16 -> 14400000 | D5: ='1. Drivers (base)'!D6*'0. Scenario & Read me'!$C$15*'1. Drivers (base)'!D16*'0. Scenario & Read me'!$C$16 -> 73500000 | E5: ='1. Drivers (base)'!E6*'0. Scenario & Read me'!$C$15*'1. Drivers (base)'!E16*'0. Scenario & Read me'!$C$16 -> 234000000 | F5: ='1. Drivers (base)'!F6*'0. Scenario & Read me'!$C$15*'1. Drivers (base)'!F16*'0. Scenario & Read me'!$C$16 -> 468000000 | G5: ='1. Drivers (base)'!G6*'0. Scenario & Read me'!$C$15*'1. Drivers (base)'!G16*'0. Scenario & Read me'!$C$16 -> 825000000
A6: Commercial fees | C6: ='1. Drivers (base)'!C7*'0. Scenario & Read me'!$C$15*'1. Drivers (base)'!C17*'0. Scenario & Read me'!$C$16 -> 9000000 | D6: ='1. Drivers (base)'!D7*'0. Scenario & Read me'!$C$15*'1. Drivers (base)'!D17*'0. Scenario & Read me'!$C$16 -> 31000000 | E6: ='1. Drivers (base)'!E7*'0. Scenario & Read me'!$C$15*'1. Drivers (base)'!E17*'0. Scenario & Read me'!$C$16 -> 76800000 | F6: ='1. Drivers (base)'!F7*'0. Scenario & Read me'!$C$15*'1. Drivers (base)'!F17*'0. Scenario & Read me'!$C$16 -> 158400000 | G6: ='1. Drivers (base)'!G7*'0. Scenario & Read me'!$C$15*'1. Drivers (base)'!G17*'0. Scenario & Read me'!$C$16 -> 272000000
A7: Family fees | C7: ='1. Drivers (base)'!C8*'0. Scenario & Read me'!$C$15*'1. Drivers (base)'!C18*'0. Scenario & Read me'!$C$16 -> 3600000 | D7: ='1. Drivers (base)'!D8*'0. Scenario & Read me'!$C$15*'1. Drivers (base)'!D18*'0. Scenario & Read me'!$C$16 -> 14800000 | E7: ='1. Drivers (base)'!E8*'0. Scenario & Read me'!$C$15*'1. Drivers (base)'!E18*'0. Scenario & Read me'!$C$16 -> 38000000 | F7: ='1. Drivers (base)'!F8*'0. Scenario & Read me'!$C$15*'1. Drivers (base)'!F18*'0. Scenario & Read me'!$C$16 -> 78000000 | G7: ='1. Drivers (base)'!G8*'0. Scenario & Read me'!$C$15*'1. Drivers (base)'!G18*'0. Scenario & Read me'!$C$16 -> 140000000
A8: Grievance SaaS | C8: ='1. Drivers (base)'!C9*'0. Scenario & Read me'!$C$15*'1. Drivers (base)'!C19*'0. Scenario & Read me'!$C$16 -> 1800000 | D8: ='1. Drivers (base)'!D9*'0. Scenario & Read me'!$C$15*'1. Drivers (base)'!D19*'0. Scenario & Read me'!$C$16 -> 7600000 | E8: ='1. Drivers (base)'!E9*'0. Scenario & Read me'!$C$15*'1. Drivers (base)'!E19*'0. Scenario & Read me'!$C$16 -> 24000000 | F8: ='1. Drivers (base)'!F9*'0. Scenario & Read me'!$C$15*'1. Drivers (base)'!F19*'0. Scenario & Read me'!$C$16 -> 54600000 | G8: ='1. Drivers (base)'!G9*'0. Scenario & Read me'!$C$15*'1. Drivers (base)'!G19*'0. Scenario & Read me'!$C$16 -> 99000000
A9: Escalation fees | C9: ='1. Drivers (base)'!C10*'0. Scenario & Read me'!$C$15*'1. Drivers (base)'!C20*'0. Scenario & Read me'!$C$16 -> 500000 | D9: ='1. Drivers (base)'!D10*'0. Scenario & Read me'!$C$15*'1. Drivers (base)'!D20*'0. Scenario & Read me'!$C$16 -> 3120000 | E9: ='1. Drivers (base)'!E10*'0. Scenario & Read me'!$C$15*'1. Drivers (base)'!E20*'0. Scenario & Read me'!$C$16 -> 10800000 | F9: ='1. Drivers (base)'!F10*'0. Scenario & Read me'!$C$15*'1. Drivers (base)'!F20*'0. Scenario & Read me'!$C$16 -> 25200000 | G9: ='1. Drivers (base)'!G10*'0. Scenario & Read me'!$C$15*'1. Drivers (base)'!G20*'0. Scenario & Read me'!$C$16 -> 46400000
A10: Private Court subs | C10: ='1. Drivers (base)'!C11*'0. Scenario & Read me'!$C$15*'1. Drivers (base)'!C21*'0. Scenario & Read me'!$C$16 -> 900000 | D10: ='1. Drivers (base)'!D11*'0. Scenario & Read me'!$C$15*'1. Drivers (base)'!D21*'0. Scenario & Read me'!$C$16 -> 5040000 | E10: ='1. Drivers (base)'!E11*'0. Scenario & Read me'!$C$15*'1. Drivers (base)'!E21*'0. Scenario & Read me'!$C$16 -> 14520000 | F10: ='1. Drivers (base)'!F11*'0. Scenario & Read me'!$C$15*'1. Drivers (base)'!F21*'0. Scenario & Read me'!$C$16 -> 31050000 | G10: ='1. Drivers (base)'!G11*'0. Scenario & Read me'!$C$15*'1. Drivers (base)'!G21*'0. Scenario & Read me'!$C$16 -> 57600000
A11: Private Court cases | C11: ='1. Drivers (base)'!C12*'0. Scenario & Read me'!$C$15*'1. Drivers (base)'!C22*'0. Scenario & Read me'!$C$16 -> 240000 | D11: ='1. Drivers (base)'!D12*'0. Scenario & Read me'!$C$15*'1. Drivers (base)'!D22*'0. Scenario & Read me'!$C$16 -> 1700000 | E11: ='1. Drivers (base)'!E12*'0. Scenario & Read me'!$C$15*'1. Drivers (base)'!E22*'0. Scenario & Read me'!$C$16 -> 5400000 | F11: ='1. Drivers (base)'!F12*'0. Scenario & Read me'!$C$15*'1. Drivers (base)'!F22*'0. Scenario & Read me'!$C$16 -> 13300000 | G11: ='1. Drivers (base)'!G12*'0. Scenario & Read me'!$C$15*'1. Drivers (base)'!G22*'0. Scenario & Read me'!$C$16 -> 26000000
A12: Academy | C12: ='1. Drivers (base)'!C13*'0. Scenario & Read me'!$C$15*'1. Drivers (base)'!C23*'0. Scenario & Read me'!$C$16 -> 3600000 | D12: ='1. Drivers (base)'!D13*'0. Scenario & Read me'!$C$15*'1. Drivers (base)'!D23*'0. Scenario & Read me'!$C$16 -> 15000000 | E12: ='1. Drivers (base)'!E13*'0. Scenario & Read me'!$C$15*'1. Drivers (base)'!E23*'0. Scenario & Read me'!$C$16 -> 39000000 | F12: ='1. Drivers (base)'!F13*'0. Scenario & Read me'!$C$15*'1. Drivers (base)'!F23*'0. Scenario & Read me'!$C$16 -> 81000000 | G12: ='1. Drivers (base)'!G13*'0. Scenario & Read me'!$C$15*'1. Drivers (base)'!G23*'0. Scenario & Read me'!$C$16 -> 140000000
A13: API/white-label | C13: ='1. Drivers (base)'!C14*'0. Scenario & Read me'!$C$15*'1. Drivers (base)'!C24*'0. Scenario & Read me'!$C$16 -> 1200000 | D13: ='1. Drivers (base)'!D14*'0. Scenario & Read me'!$C$15*'1. Drivers (base)'!D24*'0. Scenario & Read me'!$C$16 -> 5200000 | E13: ='1. Drivers (base)'!E14*'0. Scenario & Read me'!$C$15*'1. Drivers (base)'!E24*'0. Scenario & Read me'!$C$16 -> 14000000 | F13: ='1. Drivers (base)'!F14*'0. Scenario & Read me'!$C$15*'1. Drivers (base)'!F24*'0. Scenario & Read me'!$C$16 -> 30000000 | G13: ='1. Drivers (base)'!G14*'0. Scenario & Read me'!$C$15*'1. Drivers (base)'!G24*'0. Scenario & Read me'!$C$16 -> 56000000
A14: TOTAL
A15: Total revenue (₹) | C15: =C5+C6+C7+C8+C9+C10+C11+C12+C13 -> 35240000 | D15: =D5+D6+D7+D8+D9+D10+D11+D12+D13 -> 156960000 | E15: =E5+E6+E7+E8+E9+E10+E11+E12+E13 -> 456520000 | F15: =F5+F6+F7+F8+F9+F10+F11+F12+F13 -> 939550000 | G15: =G5+G6+G7+G8+G9+G10+G11+G12+G13 -> 1662000000
A16: Total revenue (₹ Cr) | C16: =C15/10000000 -> 3.524 | D16: =D15/10000000 -> 15.696 | E16: =E15/10000000 -> 45.652 | F16: =F15/10000000 -> 93.955 | G16: =G15/10000000 -> 166.2

Sheet 3. Costs
A1: Costs (scenario-adjusted)
A2: Opex % scaled by Opex-mult; neutral payout & infra scale with scenario volume.
C4: Year 1 | D4: Year 2 | E4: Year 3 | F4: Year 4 | G4: Year 5
A5: COGS
A6: Neutral payouts | C6: =('2. Revenue'!C5+'2. Revenue'!C6+'2. Revenue'!C7+'2. Revenue'!C11+'2. Revenue'!C9)*'1. Drivers (base)'!C31 -> 12483000 | D6: =('2. Revenue'!D5+'2. Revenue'!D6+'2. Revenue'!D7+'2. Revenue'!D11+'2. Revenue'!D9)*'1. Drivers (base)'!D31 -> 55854000 | E6: =('2. Revenue'!E5+'2. Revenue'!E6+'2. Revenue'!E7+'2. Revenue'!E11+'2. Revenue'!E9)*'1. Drivers (base)'!E31 -> 160600000 | F6: =('2. Revenue'!F5+'2. Revenue'!F6+'2. Revenue'!F7+'2. Revenue'!F11+'2. Revenue'!F9)*'1. Drivers (base)'!F31 -> 326876000 | G6: =('2. Revenue'!G5+'2. Revenue'!G6+'2. Revenue'!G7+'2. Revenue'!G11+'2. Revenue'!G9)*'1. Drivers (base)'!G31 -> 563042000
A7: Infra & 3rd-party | C7: =('1. Drivers (base)'!C6+'1. Drivers (base)'!C7+'1. Drivers (base)'!C8+'1. Drivers (base)'!C12+'1. Drivers (base)'!C10)*'0. Scenario & Read me'!$C$15*'1. Drivers (base)'!C28 -> 800400 | D7: =('1. Drivers (base)'!D6+'1. Drivers (base)'!D7+'1. Drivers (base)'!D8+'1. Drivers (base)'!D12+'1. Drivers (base)'!D10)*'0. Scenario & Read me'!$C$15*'1. Drivers (base)'!D28 -> 3676200 | E7: =('1. Drivers (base)'!E6+'1. Drivers (base)'!E7+'1. Drivers (base)'!E8+'1. Drivers (base)'!E12+'1. Drivers (base)'!E10)*'0. Scenario & Read me'!$C$15*'1. Drivers (base)'!E28 -> 9960000 | F7: =('1. Drivers (base)'!F6+'1. Drivers (base)'!F7+'1. Drivers (base)'!F8+'1. Drivers (base)'!F12+'1. Drivers (base)'!F10)*'0. Scenario & Read me'!$C$15*'1. Drivers (base)'!F28 -> 19123500 | G7: =('1. Drivers (base)'!G6+'1. Drivers (base)'!G7+'1. Drivers (base)'!G8+'1. Drivers (base)'!G12+'1. Drivers (base)'!G10)*'0. Scenario & Read me'!$C$15*'1. Drivers (base)'!G28 -> 30474000
A8: Total COGS | C8: =C6+C7 -> 13283400 | D8: =D6+D7 -> 59530200 | E8: =E6+E7 -> 170560000 | F8: =F6+F7 -> 345999500 | G8: =G6+G7 -> 593516000
A9: OpEx
A10: People | C10: ='1. Drivers (base)'!C26*'1. Drivers (base)'!C27 -> 25200000 | D10: ='1. Drivers (base)'!D26*'1. Drivers (base)'!D27 -> 58000000 | E10: ='1. Drivers (base)'!E26*'1. Drivers (base)'!E27 -> 112500000 | F10: ='1. Drivers (base)'!F26*'1. Drivers (base)'!F27 -> 186000000 | G10: ='1. Drivers (base)'!G26*'1. Drivers (base)'!G27 -> 272000000
A11: Sales & Marketing | C11: ='2. Revenue'!C15*'1. Drivers (base)'!C29*'0. Scenario & Read me'!$C$17 -> 15858000 | D11: ='2. Revenue'!D15*'1. Drivers (base)'!D29*'0. Scenario & Read me'!$C$17 -> 54936000 | E11: ='2. Revenue'!E15*'1. Drivers (base)'!E29*'0. Scenario & Read me'!$C$17 -> 127825600 | F11: ='2. Revenue'!F15*'1. Drivers (base)'!F29*'0. Scenario & Read me'!$C$17 -> 225492000 | G11: ='2. Revenue'!G15*'1. Drivers (base)'!G29*'0. Scenario & Read me'!$C$17 -> 365640000
A12: G&A & overheads | C12: ='2. Revenue'!C15*'1. Drivers (base)'!C30*'0. Scenario & Read me'!$C$17 -> 10572000 | D12: ='2. Revenue'!D15*'1. Drivers (base)'!D30*'0. Scenario & Read me'!$C$17 -> 34531200 | E12: ='2. Revenue'!E15*'1. Drivers (base)'!E30*'0. Scenario & Read me'!$C$17 -> 82173600 | F12: ='2. Revenue'!F15*'1. Drivers (base)'!F30*'0. Scenario & Read me'!$C$17 -> 150328000 | G12: ='2. Revenue'!G15*'1. Drivers (base)'!G30*'0. Scenario & Read me'!$C$17 -> 249300000
A13: Total OpEx | C13: =C10+C11+C12 -> 51630000 | D13: =D10+D11+D12 -> 147467200 | E13: =E10+E11+E12 -> 322499200 | F13: =F10+F11+F12 -> 561820000 | G13: =G10+G11+G12 -> 886940000

Sheet 4. P&L
A1: P&L (active scenario)
A2: Revenue − COGS = Gross profit; − OpEx = EBITDA.
C4: Year 1 | D4: Year 2 | E4: Year 3 | F4: Year 4 | G4: Year 5
A5: Revenue | C5: ='2. Revenue'!C15 -> 35240000 | D5: ='2. Revenue'!D15 -> 156960000 | E5: ='2. Revenue'!E15 -> 456520000 | F5: ='2. Revenue'!F15 -> 939550000 | G5: ='2. Revenue'!G15 -> 1662000000
A6: COGS | C6: =-'3. Costs'!C8 -> -13283400 | D6: =-'3. Costs'!D8 -> -59530200 | E6: =-'3. Costs'!E8 -> -170560000 | F6: =-'3. Costs'!F8 -> -345999500 | G6: =-'3. Costs'!G8 -> -593516000
A7: Gross profit | C7: =C5+C6 -> 21956600 | D7: =D5+D6 -> 97429800 | E7: =E5+E6 -> 285960000 | F7: =F5+F6 -> 593550500 | G7: =G5+G6 -> 1068484000
A8: Gross margin | C8: =C7/C5 -> 0.62305902 | D8: =D7/D5 -> 0.62073012 | E8: =E7/E5 -> 0.62639096 | F8: =F7/F5 -> 0.63173913 | G8: =G7/G5 -> 0.64289049
A9: OpEx | C9: =-'3. Costs'!C13 -> -51630000 | D9: =-'3. Costs'!D13 -> -147467200 | E9: =-'3. Costs'!E13 -> -322499200 | F9: =-'3. Costs'!F13 -> -561820000 | G9: =-'3. Costs'!G13 -> -886940000
A10: EBITDA | C10: =C7+C9 -> -29673400 | D10: =D7+D9 -> -50037400 | E10: =E7+E9 -> -36539200 | F10: =F7+F9 -> 31730500 | G10: =G7+G9 -> 181544000
A11: EBITDA margin | C11: =C10/C5 -> -0.84203746 | D11: =D10/D5 -> -0.31879077 | E11: =E10/E5 -> -0.080038553 | F11: =F10/F5 -> 0.033772019 | G11: =G10/G5 -> 0.10923225
A13: EBITDA (₹ Cr) | C13: =C10/10000000 -> -2.96734 | D13: =D10/10000000 -> -5.00374 | E13: =E10/10000000 -> -3.65392 | F13: =F10/10000000 -> 3.17305 | G13: =G10/10000000 -> 18.1544

Sheet 5. Unit econ (CAC-LTV)
A1: Unit Economics — CAC / LTV
A2: Blended across paying customers; CAC scaled by CAC-mult.
C4: Year 1 | D4: Year 2 | E4: Year 3 | F4: Year 4 | G4: Year 5
A5: Customers acquired (proxy) | C5: =('1. Drivers (base)'!C6+'1. Drivers (base)'!C7+'1. Drivers (base)'!C8+'1. Drivers (base)'!C9+'1. Drivers (base)'!C11+'1. Drivers (base)'!C13+'1. Drivers (base)'!C14)*'0. Scenario & Read me'!$C$15 -> 6677 | D5: =('1. Drivers (base)'!D6+'1. Drivers (base)'!D7+'1. Drivers (base)'!D8+'1. Drivers (base)'!D9+'1. Drivers (base)'!D11+'1. Drivers (base)'!D13+'1. Drivers (base)'!D14)*'0. Scenario & Read me'!$C$15 -> 32628 | E5: =('1. Drivers (base)'!E6+'1. Drivers (base)'!E7+'1. Drivers (base)'!E8+'1. Drivers (base)'!E9+'1. Drivers (base)'!E11+'1. Drivers (base)'!E13+'1. Drivers (base)'!E14)*'0. Scenario & Read me'!$C$15 -> 96560 | F5: =('1. Drivers (base)'!F6+'1. Drivers (base)'!F7+'1. Drivers (base)'!F8+'1. Drivers (base)'!F9+'1. Drivers (base)'!F11+'1. Drivers (base)'!F13+'1. Drivers (base)'!F14)*'0. Scenario & Read me'!$C$15 -> 193150 | G5: =('1. Drivers (base)'!G6+'1. Drivers (base)'!G7+'1. Drivers (base)'!G8+'1. Drivers (base)'!G9+'1. Drivers (base)'!G11+'1. Drivers (base)'!G13+'1. Drivers (base)'!G14)*'0. Scenario & Read me'!$C$15 -> 322320
A6: CAC (₹) | C6: ='1. Drivers (base)'!C33*'0. Scenario & Read me'!$C$18 -> 1200 | D6: ='1. Drivers (base)'!D33*'0. Scenario & Read me'!$C$18 -> 1100 | E6: ='1. Drivers (base)'!E33*'0. Scenario & Read me'!$C$18 -> 1000 | F6: ='1. Drivers (base)'!F33*'0. Scenario & Read me'!$C$18 -> 950 | G6: ='1. Drivers (base)'!G33*'0. Scenario & Read me'!$C$18 -> 900
A7: Revenue per customer (₹) | C7: ='2. Revenue'!C15/C5 -> 5277.8194 | D7: ='2. Revenue'!D15/D5 -> 4810.5921 | E7: ='2. Revenue'!E15/E5 -> 4727.8376 | F7: ='2. Revenue'!F15/F5 -> 4864.3541 | G7: ='2. Revenue'!G15/G5 -> 5156.3663
A8: Contribution margin | C8: ='1. Drivers (base)'!C35 -> 0.55 | D8: ='1. Drivers (base)'!D35 -> 0.56 | E8: ='1. Drivers (base)'!E35 -> 0.58 | F8: ='1. Drivers (base)'!F35 -> 0.6 | G8: ='1. Drivers (base)'!G35 -> 0.62
A9: Avg life (yrs) | C9: ='1. Drivers (base)'!C34 -> 2 | D9: ='1. Drivers (base)'!D34 -> 2.2 | E9: ='1. Drivers (base)'!E34 -> 2.5 | F9: ='1. Drivers (base)'!F34 -> 2.7 | G9: ='1. Drivers (base)'!G34 -> 3
A10: LTV (₹) | C10: =C7*C8*C9 -> 5805.6013 | D10: =D7*D8*D9 -> 5926.6495 | E10: =E7*E8*E9 -> 6855.3645 | F10: =F7*F8*F9 -> 7880.2537 | G10: =G7*G8*G9 -> 9590.8414
A11: LTV / CAC | C11: =C10/C6 -> 4.8380011 | D11: =D10/D6 -> 5.3878632 | E11: =E10/E6 -> 6.8553645 | F11: =F10/F6 -> 8.2950039 | G11: =G10/G6 -> 10.65649
A12: CAC payback (months) | C12: =C6/((C7*C8)/12) -> 4.9607264 | D12: =D6/((D7*D8)/12) -> 4.8999017 | E12: =E6/((E7*E8)/12) -> 4.3761349 | F12: =F6/((F7*F8)/12) -> 3.9059656 | G12: =G6/((G7*G8)/12) -> 3.3782229
A14: Target: LTV/CAC ≥ 3.0x and payback < 12 months are healthy SaaS benchmarks.

Sheet 6. Cash & runway
A1: Cash, Runway & Funding Need
A2: EBITDA proxy for operating cash; cumulative shows max cash needed (funding requirement).
C4: Year 1 | D4: Year 2 | E4: Year 3 | F4: Year 4 | G4: Year 5
A5: EBITDA (₹ Cr) | C5: ='4. P&L'!C10/10000000 -> -2.96734 | D5: ='4. P&L'!D10/10000000 -> -5.00374 | E5: ='4. P&L'!E10/10000000 -> -3.65392 | F5: ='4. P&L'!F10/10000000 -> 3.17305 | G5: ='4. P&L'!G10/10000000 -> 18.1544
A6: Cumulative cash (₹ Cr) | C6: =C5 -> -2.96734 | D6: =C6+D5 -> -7.97108 | E6: =D6+E5 -> -11.625 | F6: =E6+F5 -> -8.45195 | G6: =F6+G5 -> 9.70245
A8: Funding need (₹ Cr) = deepest cumulative trough | C8: =-MIN(C6:G6) -> 11.625
A9: Break-even year (first EBITDA>0) | C9: =IFERROR(MATCH(TRUE(),INDEX(C5:G5>0,0),0),"beyond Yr5") -> 4
A11: Funding need is the maximum cumulative cash shortfall before the business self-funds. Raise with ~30–50% buffer.

Sheet 7. Sensitivity
A1: Sensitivity — Year-5 EBITDA (₹ Cr)
A2: Which drivers move the outcome most. Each row flexes ONE driver ±20% on the active scenario (illustrative, manual deltas).
A4: Driver flexed | B4: −20% | C4: Base (active) | D4: +20% | E4: Swing (₹ Cr) | F4: Rank
A5: Volume (all) | B5: ='4. P&L'!G10/10000000-('4. P&L'!G10/10000000)*1.85*0.2 -> 11.437272 | C5: ='4. P&L'!G10/10000000 -> 18.1544 | D5: ='4. P&L'!G10/10000000+('4. P&L'!G10/10000000)*1.85*0.2 -> 24.871528 | E5: =ABS(D5-B5) -> 13.434256 | F5: =RANK(E5,$E$5:$E$10) -> 1
A6: Price realisation | B6: ='4. P&L'!G10/10000000-('4. P&L'!G10/10000000)*1.78*0.2 -> 11.691434 | C6: ='4. P&L'!G10/10000000 -> 18.1544 | D6: ='4. P&L'!G10/10000000+('4. P&L'!G10/10000000)*1.78*0.2 -> 24.617366 | E6: =ABS(D6-B6) -> 12.925933 | F6: =RANK(E6,$E$5:$E$10) -> 2
A7: Neutral payout % | B7: ='4. P&L'!G10/10000000+('4. P&L'!G10/10000000)*0.3*0.2 -> 19.243664 | C7: ='4. P&L'!G10/10000000 -> 18.1544 | D7: ='4. P&L'!G10/10000000-('4. P&L'!G10/10000000)*0.3*0.2 -> 17.065136 | E7: =ABS(D7-B7) -> 2.178528 | F7: =RANK(E7,$E$5:$E$10) -> 4
A8: S&M % of revenue | B8: ='4. P&L'!G10/10000000+('4. P&L'!G10/10000000)*0.22*0.2 -> 18.953194 | C8: ='4. P&L'!G10/10000000 -> 18.1544 | D8: ='4. P&L'!G10/10000000-('4. P&L'!G10/10000000)*0.22*0.2 -> 17.355606 | E8: =ABS(D8-B8) -> 1.5975872 | F8: =RANK(E8,$E$5:$E$10) -> 5
A9: Headcount cost | B9: ='4. P&L'!G10/10000000+('4. P&L'!G10/10000000)*0.35*0.2 -> 19.425208 | C9: ='4. P&L'!G10/10000000 -> 18.1544 | D9: ='4. P&L'!G10/10000000-('4. P&L'!G10/10000000)*0.35*0.2 -> 16.883592 | E9: =ABS(D9-B9) -> 2.541616 | F9: =RANK(E9,$E$5:$E$10) -> 3
A10: Infra cost/case | B10: ='4. P&L'!G10/10000000+('4. P&L'!G10/10000000)*0.06*0.2 -> 18.372253 | C10: ='4. P&L'!G10/10000000 -> 18.1544 | D10: ='4. P&L'!G10/10000000-('4. P&L'!G10/10000000)*0.06*0.2 -> 17.936547 | E10: =ABS(D10-B10) -> 0.4357056 | F10: =RANK(E10,$E$5:$E$10) -> 6
A12: Read: the largest 'Swing' = the driver Year-5 EBITDA is most sensitive to. Volume and price dominate; cost ratios matter less per 20% move.

Sheet 8. Assumptions log
A1: Assumptions Log
A2: Every material input with rationale/source and owner. The audit trail for the model.
A4: Assumption | B4: Value / basis | C4: Rationale / source | D4: Owner
A5: NBFC volume ramp | B5: 6k→300k over 5y | C5: Clause-driven bulk intake from lender partners; conservative vs SAMA/Presolv360 scale | D5: Founder
A6: NBFC blended fee | B6: ₹2,400–2,750/case | C6: Conciliation + prob-weighted arbitration; below DRT cost | D6: Founder
A7: Commercial fee/case | B7: ₹60k–68k | C7: Higher value, lower volume; institutional benchmark | D7: Legal/Founder
A8: Neutral payout % | B8: 43–45% of case fees | C8: Share to neutrals (COGS); institutional norm | D8: Ops
A9: S&M % of revenue | B9: 45%→22% | C9: Heavy early acquisition, improving with brand & referrals | D9: Founder/CFO
A10: G&A % of revenue | B10: 30%→15% | C10: Operating leverage as scale grows | D10: CFO
A11: Headcount | B11: 18→170 | C11: Scales sub-linearly to revenue (automation) | D11: COO
A12: Loaded salary/head | B12: ₹14–16 L | C12: Blended eng/ops/GTM/G&A, India market | D12: HR/CFO
A13: CAC (base) | B13: ₹900–1,200 | C13: Blended; bulk lender channel lowers CAC | D13: Marketing
A14: Customer life | B14: 2.0–3.0 yrs | C14: Institutional + Private Court stickiness | D14: Founder
A15: Scenario: Bull | B15: Vol ×1.4, Price ×1.1, Opex ×0.9, CAC ×0.85 | C15: Faster lender adoption + efficiency | D15: Founder
... A17: FX (if USD view) | B17: ₹83/USD | C17: Indicative; update at use | D17: CFO
