Workbook

Sheet 0. Read me
A1: EQUATOR RESOLUTION — Financial Model
A2: Driver-based 5-year plan (INR). Blue cells are inputs you can change; everything else is a live formula.
A4: How this model works
A5: • All assumptions live on the '1. Drivers' tab. Cells in BLUE are inputs — change them and the whole model recalculates.
A6: • Black numbers are formulas; green numbers (if any) pull from other tabs. Do not overtype formulas.
A7: • Revenue is built bottom-up per line of business on '2. Revenue': case volumes x price, ramping each year.
A8: • '3. Unit Economics' shows contribution per case for the flagship NBFC and Commercial pillars.
A9: • '4. Costs & Headcount' builds people + infrastructure + S&M + G&A. '5. P&L' rolls everything up.
A10: • '6. Summary' shows the headline trajectory and break-even. Figures are INR; ₹1 Cr = ₹10,000,000.
A11: • These are planning assumptions, NOT a forecast. Pressure-test the BLUE inputs against your real pipeline and pricing.
A13: Tabs
A14: ▸ 1. Drivers — all assumptions (edit here)
... A19: ▸ 6. Summary — headline + break-even

Sheet 1. Drivers
A1: Drivers & Assumptions
A2: Edit the BLUE cells. Everything else in the model references these.
A4: ₹ unless noted | C4: Year 1 | D4: Year 2 | E4: Year 3 | F4: Year 4 | G4: Year 5
A5: A. NBFC ↔ Borrower (volume engine)
A6: New NBFC cases onboarded (#) | C6: 6000 | D6: 30000 | E6: 90000 | F6: 180000 | G6: 300000
A7: Conciliation fee per case (₹) | C7: 1500 | D7: 1500 | E7: 1600 | F7: 1600 | G7: 1700
A8: % reaching paid conciliation | C8: 0.85 | D8: 0.85 | E8: 0.85 | F8: 0.85 | G8: 0.85
A9: Arbitration fee per escalated case (₹) | C9: 6000 | D9: 6000 | E9: 6500 | F9: 6500 | G9: 7000
A10: % escalating to arbitration | C10: 0.2 | D10: 0.2 | E10: 0.2 | F10: 0.18 | G10: 0.18
A11: B. Commercial / Contractual
A12: New commercial cases (#) | C12: 150 | D12: 500 | E12: 1200 | F12: 2400 | G12: 4000
A13: Avg fee per commercial case (₹) | C13: 60000 | D13: 62000 | E13: 64000 | F13: 66000 | G13: 68000
A14: C. Family / Marital
A15: New family mediation cases (#) | C15: 200 | D15: 800 | E15: 2000 | F15: 4000 | G15: 7000
A16: Avg fee per family case (₹) | C16: 18000 | D16: 18500 | E16: 19000 | F16: 19500 | G16: 20000
A17: D. Enterprise Grievance & POSH (SaaS)
A18: Enterprise clients (#) | C18: 10 | D18: 40 | E18: 120 | F18: 260 | G18: 450
A19: Avg annual SaaS per client (₹) | C19: 180000 | D19: 190000 | E19: 200000 | F19: 210000 | G19: 220000
A20: Escalation cases to EDRS (#) | C20: 20 | D20: 120 | E20: 400 | F20: 900 | G20: 1600
A21: Avg escalation fee (₹) | C21: 25000 | D21: 26000 | E21: 27000 | F21: 28000 | G21: 29000
A22: E. Private Court (SaaS for neutrals)
A23: Private Court subscribers (#) | C23: 15 | D23: 80 | E23: 220 | F23: 450 | G23: 800
A24: Avg annual subscription (₹) | C24: 60000 | D24: 63000 | E24: 66000 | F24: 69000 | G24: 72000
A25: Private Court per-case fees — cases (#) | C25: 300 | D25: 2000 | E25: 6000 | F25: 14000 | G25: 26000
A26: Per-case fee (₹) | C26: 800 | D26: 850 | E26: 900 | F26: 950 | G26: 1000
A27: F. Academy (training)
A28: Paid learners / certifications (#) | C28: 300 | D28: 1200 | E28: 3000 | F28: 6000 | G28: 10000
A29: Avg course/cert fee (₹) | C29: 12000 | D29: 12500 | E29: 13000 | F29: 13500 | G29: 14000
A30: G. API & White-label
A31: API / white-label clients (#) | C31: 2 | D31: 8 | E31: 20 | F31: 40 | G31: 70
A32: Avg annual platform fee (₹) | C32: 600000 | D32: 650000 | E32: 700000 | F32: 750000 | G32: 800000
A33: H. Cost drivers
A34: Avg fully-loaded salary / head / yr (₹) | C34: 1400000 | D34: 1450000 | E34: 1500000 | F34: 1550000 | G34: 1600000
A35: Total headcount (#) | C35: 18 | D35: 40 | E35: 75 | F35: 120 | G35: 170
A36: Cloud + 3rd-party cost per case (₹) | C36: 120 | D36: 110 | E36: 100 | F36: 95 | G36: 90
A37: Sales & Marketing (% of revenue) | C37: 0.45 | D37: 0.35 | E37: 0.28 | F37: 0.24 | G37: 0.22
A38: G&A + overheads (% of revenue) | C38: 0.3 | D38: 0.22 | E38: 0.18 | F38: 0.16 | G38: 0.15
A39: Neutral payout (% of case-fee revenue) | C39: 0.45 | D39: 0.45 | E39: 0.44 | F39: 0.44 | G39: 0.43

Sheet 2. Revenue
A1: Revenue Build — by line of business
A2: Bottom-up: volumes x price. All cells are formulas referencing the Drivers tab.
A4: ₹ unless noted | C4: Year 1 | D4: Year 2 | E4: Year 3 | F4: Year 4 | G4: Year 5
A5: NBFC ↔ Borrower
A6: Conciliation fees | C6: ='1. Drivers'!C6*'1. Drivers'!C8*'1. Drivers'!C7 -> 7650000 | D6: ='1. Drivers'!D6*'1. Drivers'!D8*'1. Drivers'!D7 -> 38250000 | E6: ='1. Drivers'!E6*'1. Drivers'!E8*'1. Drivers'!E7 -> 122400000 | F6: ='1. Drivers'!F6*'1. Drivers'!F8*'1. Drivers'!F7 -> 244800000 | G6: ='1. Drivers'!G6*'1. Drivers'!G8*'1. Drivers'!G7 -> 433500000
A7: Arbitration fees | C7: ='1. Drivers'!C6*'1. Drivers'!C10*'1. Drivers'!C9 -> 7200000 | D7: ='1. Drivers'!D6*'1. Drivers'!D10*'1. Drivers'!D9 -> 36000000 | E7: ='1. Drivers'!E6*'1. Drivers'!E10*'1. Drivers'!E9 -> 117000000 | F7: ='1. Drivers'!F6*'1. Drivers'!F10*'1. Drivers'!F9 -> 210600000 | G7: ='1. Drivers'!G6*'1. Drivers'!G10*'1. Drivers'!G9 -> 378000000
A8: NBFC subtotal | C8: =C6+C7 -> 14850000 | D8: =D6+D7 -> 74250000 | E8: =E6+E7 -> 239400000 | F8: =F6+F7 -> 455400000 | G8: =G6+G7 -> 811500000
A9: Commercial / Family
A10: Commercial case fees | C10: ='1. Drivers'!C12*'1. Drivers'!C13 -> 9000000 | D10: ='1. Drivers'!D12*'1. Drivers'!D13 -> 31000000 | E10: ='1. Drivers'!E12*'1. Drivers'!E13 -> 76800000 | F10: ='1. Drivers'!F12*'1. Drivers'!F13 -> 158400000 | G10: ='1. Drivers'!G12*'1. Drivers'!G13 -> 272000000
A11: Family mediation fees | C11: ='1. Drivers'!C15*'1. Drivers'!C16 -> 3600000 | D11: ='1. Drivers'!D15*'1. Drivers'!D16 -> 14800000 | E11: ='1. Drivers'!E15*'1. Drivers'!E16 -> 38000000 | F11: ='1. Drivers'!F15*'1. Drivers'!F16 -> 78000000 | G11: ='1. Drivers'!G15*'1. Drivers'!G16 -> 140000000
A12: Enterprise Grievance & POSH
A13: Grievance SaaS (subscriptions) | C13: ='1. Drivers'!C18*'1. Drivers'!C19 -> 1800000 | D13: ='1. Drivers'!D18*'1. Drivers'!D19 -> 7600000 | E13: ='1. Drivers'!E18*'1. Drivers'!E19 -> 24000000 | F13: ='1. Drivers'!F18*'1. Drivers'!F19 -> 54600000 | G13: ='1. Drivers'!G18*'1. Drivers'!G19 -> 99000000
A14: POSH/grievance escalation fees | C14: ='1. Drivers'!C20*'1. Drivers'!C21 -> 500000 | D14: ='1. Drivers'!D20*'1. Drivers'!D21 -> 3120000 | E14: ='1. Drivers'!E20*'1. Drivers'!E21 -> 10800000 | F14: ='1. Drivers'!F20*'1. Drivers'!F21 -> 25200000 | G14: ='1. Drivers'!G20*'1. Drivers'!G21 -> 46400000
A15: Private Court (SaaS)
A16: Private Court subscriptions | C16: ='1. Drivers'!C23*'1. Drivers'!C24 -> 900000 | D16: ='1. Drivers'!D23*'1. Drivers'!D24 -> 5040000 | E16: ='1. Drivers'!E23*'1. Drivers'!E24 -> 14520000 | F16: ='1. Drivers'!F23*'1. Drivers'!F24 -> 31050000 | G16: ='1. Drivers'!G23*'1. Drivers'!G24 -> 57600000
A17: Private Court per-case fees | C17: ='1. Drivers'!C25*'1. Drivers'!C26 -> 240000 | D17: ='1. Drivers'!D25*'1. Drivers'!D26 -> 1700000 | E17: ='1. Drivers'!E25*'1. Drivers'!E26 -> 5400000 | F17: ='1. Drivers'!F25*'1. Drivers'!F26 -> 13300000 | G17: ='1. Drivers'!G25*'1. Drivers'!G26 -> 26000000
A18: Academy & API
A19: Academy course/cert fees | C19: ='1. Drivers'!C28*'1. Drivers'!C29 -> 3600000 | D19: ='1. Drivers'!D28*'1. Drivers'!D29 -> 15000000 | E19: ='1. Drivers'!E28*'1. Drivers'!E29 -> 39000000 | F19: ='1. Drivers'!F28*'1. Drivers'!F29 -> 81000000 | G19: ='1. Drivers'!G28*'1. Drivers'!G29 -> 140000000
A20: API / white-label fees | C20: ='1. Drivers'!C31*'1. Drivers'!C32 -> 1200000 | D20: ='1. Drivers'!D31*'1. Drivers'!D32 -> 5200000 | E20: ='1. Drivers'!E31*'1. Drivers'!E32 -> 14000000 | F20: ='1. Drivers'!F31*'1. Drivers'!F32 -> 30000000 | G20: ='1. Drivers'!G31*'1. Drivers'!G32 -> 56000000
A21: TOTAL
A22: Total revenue (₹) | C22: =SUM(C8,C10,C11,C13,C14,C16,C17,C19,C20) -> 35690000 | D22: =SUM(D8,D10,D11,D13,D14,D16,D17,D19,D20) -> 157710000 | E22: =SUM(E8,E10,E11,E13,E14,E16,E17,E19,E20) -> 461920000 | F22: =SUM(F8,F10,F11,F13,F14,F16,F17,F19,F20) -> 926950000 | G22: =SUM(G8,G10,G11,G13,G14,G16,G17,G19,G20) -> 1648500000
A24: Total revenue (₹ Crore) | C24: =C22/10000000 -> 3.569 | D24: =D22/10000000 -> 15.771 | E24: =E22/10000000 -> 46.192 | F24: =F22/10000000 -> 92.695 | G24: =G22/10000000 -> 164.85
A25: YoY growth | C25: — | D25: =D22/C22-1 -> 3.4188848 | E25: =E22/D22-1 -> 1.9289202 | F25: =F22/E22-1 -> 1.0067328 | G25: =G22/F22-1 -> 0.77841308

Sheet 3. Unit Economics
A1: Unit Economics — per case
A2: Contribution per case for the flagship pillars. Formulas reference Drivers.
A4: Reference year: Year 3 (steady-state ramp)
A5: Metric | B5: NBFC case | C5: Commercial case
A6: Avg revenue per case (₹) | B6: ='1. Drivers'!E8*'1. Drivers'!E7+'1. Drivers'!E10*'1. Drivers'!E9 -> 2660 | C6: ='1. Drivers'!E13 -> 64000
A7: Less: neutral payout | B7: =-B6*'1. Drivers'!E39 -> -1170.4 | C7: =-C6*'1. Drivers'!E39 -> -28160
A8: Less: infra / 3rd-party per case | B8: =-'1. Drivers'!E36 -> -100 | C8: =-'1. Drivers'!E36 -> -100
A9: Contribution per case (₹) | B9: =B6+B7+B8 -> 1389.6 | C9: =C6+C7+C8 -> 35740
A10: Contribution margin | B10: =B9/B6 -> 0.52240602 | C10: =C9/C6 -> 0.5584375
A12: Notes
A13: • NBFC revenue/case blends the paid-conciliation fee and the probability-weighted arbitration fee.
A14: • Neutral payout is the share of case fees paid to mediators/arbitrators (COGS).
A15: • Excludes S&M and G&A (those are modelled at the company level on the P&L).
A16: • Commercial cases carry far higher absolute contribution; NBFC wins on volume.

Sheet 4. Costs & Headcount
A1: Costs & Headcount
A2: People + infrastructure + S&M + G&A + neutral payout. Formulas reference Drivers and Revenue.
A4: ₹ unless noted | C4: Year 1 | D4: Year 2 | E4: Year 3 | F4: Year 4 | G4: Year 5
A5: Cost of service (COGS)
A6: Neutral payouts | C6: =('2. Revenue'!C8+'2. Revenue'!C10+'2. Revenue'!C11+'2. Revenue'!C14+'2. Revenue'!C17)*'1. Drivers'!C39 -> 12685500 | D6: =('2. Revenue'!D8+'2. Revenue'!D10+'2. Revenue'!D11+'2. Revenue'!D14+'2. Revenue'!D17)*'1. Drivers'!D39 -> 56191500 | E6: =('2. Revenue'!E8+'2. Revenue'!E10+'2. Revenue'!E11+'2. Revenue'!E14+'2. Revenue'!E17)*'1. Drivers'!E39 -> 162976000 | F6: =('2. Revenue'!F8+'2. Revenue'!F10+'2. Revenue'!F11+'2. Revenue'!F14+'2. Revenue'!F17)*'1. Drivers'!F39 -> 321332000 | G6: =('2. Revenue'!G8+'2. Revenue'!G10+'2. Revenue'!G11+'2. Revenue'!G14+'2. Revenue'!G17)*'1. Drivers'!G39 -> 557237000
A7: Infrastructure & 3rd-party (per case) | C7: =('1. Drivers'!C6+'1. Drivers'!C12+'1. Drivers'!C15+'1. Drivers'!C25+'1. Drivers'!C20)*'1. Drivers'!C36 -> 800400 | D7: =('1. Drivers'!D6+'1. Drivers'!D12+'1. Drivers'!D15+'1. Drivers'!D25+'1. Drivers'!D20)*'1. Drivers'!D36 -> 3676200 | E7: =('1. Drivers'!E6+'1. Drivers'!E12+'1. Drivers'!E15+'1. Drivers'!E25+'1. Drivers'!E20)*'1. Drivers'!E36 -> 9960000 | F7: =('1. Drivers'!F6+'1. Drivers'!F12+'1. Drivers'!F15+'1. Drivers'!F25+'1. Drivers'!F20)*'1. Drivers'!F36 -> 19123500 | G7: =('1. Drivers'!G6+'1. Drivers'!G12+'1. Drivers'!G15+'1. Drivers'!G25+'1. Drivers'!G20)*'1. Drivers'!G36 -> 30474000
A8: Total COGS | C8: =C6+C7 -> 13485900 | D8: =D6+D7 -> 59867700 | E8: =E6+E7 -> 172936000 | F8: =F6+F7 -> 340455500 | G8: =G6+G7 -> 587711000
A9: Operating expenses
A10: People (headcount x loaded salary) | C10: ='1. Drivers'!C35*'1. Drivers'!C34 -> 25200000 | D10: ='1. Drivers'!D35*'1. Drivers'!D34 -> 58000000 | E10: ='1. Drivers'!E35*'1. Drivers'!E34 -> 112500000 | F10: ='1. Drivers'!F35*'1. Drivers'!F34 -> 186000000 | G10: ='1. Drivers'!G35*'1. Drivers'!G34 -> 272000000
A11: Sales & Marketing | C11: ='2. Revenue'!C22*'1. Drivers'!C37 -> 16060500 | D11: ='2. Revenue'!D22*'1. Drivers'!D37 -> 55198500 | E11: ='2. Revenue'!E22*'1. Drivers'!E37 -> 129337600 | F11: ='2. Revenue'!F22*'1. Drivers'!F37 -> 222468000 | G11: ='2. Revenue'!G22*'1. Drivers'!G37 -> 362670000
A12: G&A & overheads | C12: ='2. Revenue'!C22*'1. Drivers'!C38 -> 10707000 | D12: ='2. Revenue'!D22*'1. Drivers'!D38 -> 34696200 | E12: ='2. Revenue'!E22*'1. Drivers'!E38 -> 83145600 | F12: ='2. Revenue'!F22*'1. Drivers'!F38 -> 148312000 | G12: ='2. Revenue'!G22*'1. Drivers'!G38 -> 247275000
A13: Total OpEx | C13: =SUM(C10,C11,C12) -> 51967500 | D13: =SUM(D10,D11,D12) -> 147894700 | E13: =SUM(E10,E11,E12) -> 324983200 | F13: =SUM(F10,F11,F12) -> 556780000 | G13: =SUM(G10,G11,G12) -> 881945000
A14: Memo
A15: Headcount (#) | C15: ='1. Drivers'!C35 -> 18 | D15: ='1. Drivers'!D35 -> 40 | E15: ='1. Drivers'!E35 -> 75 | F15: ='1. Drivers'!F35 -> 120 | G15: ='1. Drivers'!G35 -> 170
A16: Revenue per head (₹) | C16: ='2. Revenue'!C22/'1. Drivers'!C35 -> 1982777.8 | D16: ='2. Revenue'!D22/'1. Drivers'!D35 -> 3942750 | E16: ='2. Revenue'!E22/'1. Drivers'!E35 -> 6158933.3 | F16: ='2. Revenue'!F22/'1. Drivers'!F35 -> 7724583.3 | G16: ='2. Revenue'!G22/'1. Drivers'!G35 -> 9697058.8

Sheet 5. P&L
A1: Profit & Loss — five-year
A2: All formulas. ₹ unless noted. Gross profit = Revenue − COGS; EBITDA = Gross profit − OpEx.
A4: ₹ unless noted | C4: Year 1 | D4: Year 2 | E4: Year 3 | F4: Year 4 | G4: Year 5
A5: Revenue | C5: ='2. Revenue'!C22 -> 35690000 | D5: ='2. Revenue'!D22 -> 157710000 | E5: ='2. Revenue'!E22 -> 461920000 | F5: ='2. Revenue'!F22 -> 926950000 | G5: ='2. Revenue'!G22 -> 1648500000
A6: Cost of service (COGS) | C6: =-'4. Costs & Headcount'!C8 -> -13485900 | D6: =-'4. Costs & Headcount'!D8 -> -59867700 | E6: =-'4. Costs & Headcount'!E8 -> -172936000 | F6: =-'4. Costs & Headcount'!F8 -> -340455500 | G6: =-'4. Costs & Headcount'!G8 -> -587711000
A7: Gross profit | C7: =C5+C6 -> 22204100 | D7: =D5+D6 -> 97842300 | E7: =E5+E6 -> 288984000 | F7: =F5+F6 -> 586494500 | G7: =G5+G6 -> 1060789000
A8: Gross margin | C8: =C7/C5 -> 0.62213785 | D8: =D7/D5 -> 0.62039376 | E8: =E7/E5 -> 0.62561483 | F8: =F7/F5 -> 0.63271428 | G8: =G7/G5 -> 0.64348741
A9: People | C9: =-'4. Costs & Headcount'!C10 -> -25200000 | D9: =-'4. Costs & Headcount'!D10 -> -58000000 | E9: =-'4. Costs & Headcount'!E10 -> -112500000 | F9: =-'4. Costs & Headcount'!F10 -> -186000000 | G9: =-'4. Costs & Headcount'!G10 -> -272000000
A10: Sales & Marketing | C10: =-'4. Costs & Headcount'!C11 -> -16060500 | D10: =-'4. Costs & Headcount'!D11 -> -55198500 | E10: =-'4. Costs & Headcount'!E11 -> -129337600 | F10: =-'4. Costs & Headcount'!F11 -> -222468000 | G10: =-'4. Costs & Headcount'!G11 -> -362670000
A11: G&A & overheads | C11: =-'4. Costs & Headcount'!C12 -> -10707000 | D11: =-'4. Costs & Headcount'!D12 -> -34696200 | E11: =-'4. Costs & Headcount'!E12 -> -83145600 | F11: =-'4. Costs & Headcount'!F12 -> -148312000 | G11: =-'4. Costs & Headcount'!G12 -> -247275000
A12: EBITDA | C12: =C7+C9+C10+C11 -> -29763400 | D12: =D7+D9+D10+D11 -> -50052400 | E12: =E7+E9+E10+E11 -> -35999200 | F12: =F7+F9+F10+F11 -> 29714500 | G12: =G7+G9+G10+G11 -> 178844000
A13: EBITDA margin | C13: =C12/C5 -> -0.83394228 | D13: =D12/D5 -> -0.31736986 | E13: =E12/E5 -> -0.077933841 | F13: =F12/F5 -> 0.032056206 | G13: =G12/G5 -> 0.10848893
A15: Revenue (₹ Cr) | C15: =C5/10000000 -> 3.569 | D15: =D5/10000000 -> 15.771 | E15: =E5/10000000 -> 46.192 | F15: =F5/10000000 -> 92.695 | G15: =G5/10000000 -> 164.85
A16: EBITDA (₹ Cr) | C16: =C12/10000000 -> -2.97634 | D16: =D12/10000000 -> -5.00524 | E16: =E12/10000000 -> -3.59992 | F16: =F12/10000000 -> 2.97145 | G16: =G12/10000000 -> 17.8844

Sheet 6. Summary
A1: Summary — headline trajectory & break-even
A2: Pulls from the P&L. The chart visualises revenue vs. EBITDA.
A4: ₹ unless noted | C4: Year 1 | D4: Year 2 | E4: Year 3 | F4: Year 4 | G4: Year 5
A5: Revenue (₹ Cr) | C5: ='5. P&L'!C5/10000000 -> 3.569 | D5: ='5. P&L'!D5/10000000 -> 15.771 | E5: ='5. P&L'!E5/10000000 -> 46.192 | F5: ='5. P&L'!F5/10000000 -> 92.695 | G5: ='5. P&L'!G5/10000000 -> 164.85
A6: EBITDA (₹ Cr) | C6: ='5. P&L'!C12/10000000 -> -2.97634 | D6: ='5. P&L'!D12/10000000 -> -5.00524 | E6: ='5. P&L'!E12/10000000 -> -3.59992 | F6: ='5. P&L'!F12/10000000 -> 2.97145 | G6: ='5. P&L'!G12/10000000 -> 17.8844
A7: EBITDA margin | C7: ='5. P&L'!C12/'5. P&L'!C5 -> -0.83394228 | D7: ='5. P&L'!D12/'5. P&L'!D5 -> -0.31736986 | E7: ='5. P&L'!E12/'5. P&L'!E5 -> -0.077933841 | F7: ='5. P&L'!F12/'5. P&L'!F5 -> 0.032056206 | G7: ='5. P&L'!G12/'5. P&L'!G5 -> 0.10848893
A8: Cumulative EBITDA (₹ Cr) | C8: =C6 -> -2.97634 | D8: =C8+D6 -> -7.98158 | E8: =D8+E6 -> -11.5815 | F8: =E8+F6 -> -8.61005 | G8: =F8+G6 -> 9.27435
A10: Headline (Year 5)
A11: Year-5 revenue (₹ Cr) | C11: =G5 -> 164.85
A12: Year-5 EBITDA (₹ Cr) | C12: =G6 -> 17.8844
A13: Year-5 EBITDA margin | C13: =G7 -> 0.10848893
A14: 5-yr cumulative EBITDA (₹ Cr) | C14: =G8 -> 9.27435
A16: Break-even: the first year EBITDA turns positive (see EBITDA row / chart). Adjust BLUE drivers to test scenarios.
