Workbook

Sheet ReadMe
B2: Equator Resolution — Commercial Vertical Financial Model
B3: Illustrative. Blue/yellow = inputs; black = formulas. Institutions earn mainly on administration fees.
B6: HOW TO USE
B7: - Edit inputs on 'Assumptions' only; other sheets recalculate.
B8: - Revenue is modelled as: admin (ad valorem) + registration + escrow for arbitration; flat fees for mediation & MSME.
B9: - The arbitrator's own fee is treated as pass-through (Equator's institutional revenue is the admin fee).
B11: IMPORTANT
B12: All figures are assumptions, not projections. Validate every input against Equator's tariff and pipeline.

Sheet Assumptions
B2: Assumptions
B3: Edit blue/yellow cells only.
B4: VOLUME & MIX
B5: Cases — Year 1 | C5: 150
B6: Cases — Year 2 | C6: 400
B7: Cases — Year 3 | C7: 900
B8: Share — arbitration | C8: 0.5
B9: Share — mediation / s.12A | C9: 0.3
B10: Share — MSME | C10: 0.2
B12: FEES & RATES
B13: Average claim value (₹) | C13: 20000000
B14: Administration fee (% of claim) | C14: 0.008
B15: Administration fee cap (₹) | C15: 2000000
B16: Registration fee (₹) | C16: 20000
B17: Escrow: avg amount held (₹) | C17: 10000000
B18: Escrow fee (% of amount) | C18: 0.004
B19: Share of arbitration cases with escrow | C19: 0.5
B20: Mediation fee to Equator (per case, ₹) | C20: 60000
B21: MSME fee to Equator (per case, ₹) | C21: 25000
B22: Variable cost per case (₹) | C22: 3000
B24: ANNUAL FIXED COSTS ₹ | C24: Year 1 | D24: Year 2 | E24: Year 3
B25: Technology & platform | C25: 3000000 | D25: 4500000 | E25: 6500000
B26: Salaries (ops & case managers) | C26: 5400000 | D26: 9000000 | E26: 15000000
B27: Panel & neutral development | C27: 1000000 | D27: 1500000 | E27: 2500000
B28: Marketing & BD | C28: 3500000 | D28: 5000000 | E28: 7000000
B29: Legal & compliance | C29: 1200000 | D29: 1600000 | E29: 2200000
B30: Admin & overhead | C30: 1500000 | D30: 2200000 | E30: 3200000
B31: Total fixed costs | C31: =SUM(C25:C30) -> 15600000 | D31: =SUM(D25:D30) -> 23800000 | E31: =SUM(E25:E30) -> 36400000

Sheet PnL
C4: Year 1 | D4: Year 2 | E4: Year 3
B6: Per-case revenue (blended, ₹) | C6: =(Assumptions!C8*(MIN(Assumptions!C13*Assumptions!C14,Assumptions!C15)+Assumptions!C16+Assumptions!C17*Assumptions!C18*Assumptions!C19))+(Assumptions!C9*(Assumptions!C20+Assumptions!C16))+(Assumptions!C10*Assumptions!C21) -> 129000
B8: Cases | C8: =Assumptions!C5 -> 150 | D8: =Assumptions!C6 -> 400 | E8: =Assumptions!C7 -> 900
B9: Total revenue | C9: =$C$6*C8 -> 19350000 | D9: =$C$6*D8 -> 51600000 | E9: =$C$6*E8 -> 116100000
B11: Variable costs | C11: =-Assumptions!$C$22*C8 -> -450000 | D11: =-Assumptions!$C$22*D8 -> -1200000 | E11: =-Assumptions!$C$22*E8 -> -2700000
B12: Contribution | C12: =C9+C11 -> 18900000 | D12: =D9+D11 -> 50400000 | E12: =E9+E11 -> 113400000
B13: Contribution margin | C13: =C12/C9 -> 0.97674419 | D13: =D12/D9 -> 0.97674419 | E13: =E12/E9 -> 0.97674419
B15: Fixed costs | C15: =-Assumptions!C31 -> -15600000 | D15: =-Assumptions!D31 -> -23800000 | E15: =-Assumptions!E31 -> -36400000
B16: EBITDA | C16: =C12+C15 -> 3300000 | D16: =D12+D15 -> 26600000 | E16: =E12+E15 -> 77000000
B17: EBITDA margin | C17: =C16/C9 -> 0.17054264 | D17: =D16/D9 -> 0.51550388 | E17: =E16/E9 -> 0.66322136

Sheet UnitEconomics
B2: Per-Case Economics & Break-Even
B3: Blended basis. ₹.
B5: Blended revenue per case | C5: =PnL!C6 -> 129000
B6: Variable cost per case | C6: =Assumptions!C22 -> 3000
B7: Contribution per case | C7: =C5-C6 -> 126000
B8: Contribution margin | C8: =C7/C5 -> 0.97674419
B10: Year-1 fixed costs | C10: =Assumptions!C31 -> 15600000
B11: Break-even cases (Year 1) | C11: =C10/C7 -> 123.80952
B12: Year-1 planned cases | C12: =Assumptions!C5 -> 150
B13: Margin of safety (cases) | C13: =C12-C11 -> 26.190476

Sheet Sensitivity
B4: Scenario | C4: Factor | D4: Year 1 EBITDA | E4: Year 2 EBITDA | F4: Year 3 EBITDA
B5: Conservative | C5: 0.7 | D5: =UnitEconomics!$C$7*Assumptions!$C$5*$C5-Assumptions!$C$31 -> -2370000 | E5: =UnitEconomics!$C$7*Assumptions!$C$6*$C5-Assumptions!$D$31 -> 11480000 | F5: =UnitEconomics!$C$7*Assumptions!$C$7*$C5-Assumptions!$E$31 -> 42980000
B6: Base case | C6: 1 | D6: =UnitEconomics!$C$7*Assumptions!$C$5*$C6-Assumptions!$C$31 -> 3300000 | E6: =UnitEconomics!$C$7*Assumptions!$C$6*$C6-Assumptions!$D$31 -> 26600000 | F6: =UnitEconomics!$C$7*Assumptions!$C$7*$C6-Assumptions!$E$31 -> 77000000
B7: Optimistic | C7: 1.3 | D7: =UnitEconomics!$C$7*Assumptions!$C$5*$C7-Assumptions!$C$31 -> 8970000 | E7: =UnitEconomics!$C$7*Assumptions!$C$6*$C7-Assumptions!$D$31 -> 41720000 | F7: =UnitEconomics!$C$7*Assumptions!$C$7*$C7-Assumptions!$E$31 -> 111020000
B9: Revenue scales with volume; fixed costs held per year.
